{"2":[{"word":"AA","scrabble_score":2,"wwf_score":2},{"word":"BA","scrabble_score":4,"wwf_score":5},{"word":"FA","scrabble_score":5,"wwf_score":5},{"word":"HA","scrabble_score":5,"wwf_score":4},{"word":"KA","scrabble_score":6,"wwf_score":6},{"word":"LA","scrabble_score":2,"wwf_score":3},{"word":"MA","scrabble_score":4,"wwf_score":5},{"word":"NA","scrabble_score":2,"wwf_score":3},{"word":"PA","scrabble_score":4,"wwf_score":5},{"word":"TA","scrabble_score":2,"wwf_score":2},{"word":"YA","scrabble_score":5,"wwf_score":4},{"word":"ZA","scrabble_score":11,"wwf_score":11}],"3":[{"word":"ABA","scrabble_score":5,"wwf_score":6},{"word":"AGA","scrabble_score":4,"wwf_score":5},{"word":"AHA","scrabble_score":6,"wwf_score":5},{"word":"ALA","scrabble_score":3,"wwf_score":4},{"word":"AMA","scrabble_score":5,"wwf_score":6},{"word":"ANA","scrabble_score":3,"wwf_score":4},{"word":"AVA","scrabble_score":6,"wwf_score":7},{"word":"AWA","scrabble_score":6,"wwf_score":6},{"word":"BAA","scrabble_score":5,"wwf_score":6},{"word":"BOA","scrabble_score":5,"wwf_score":6},{"word":"BRA","scrabble_score":5,"wwf_score":6},{"word":"ERA","scrabble_score":3,"wwf_score":3},{"word":"ETA","scrabble_score":3,"wwf_score":3},{"word":"GOA","scrabble_score":4,"wwf_score":5},{"word":"KEA","scrabble_score":7,"wwf_score":7},{"word":"KOA","scrabble_score":7,"wwf_score":7},{"word":"LEA","scrabble_score":3,"wwf_score":4},{"word":"MOA","scrabble_score":5,"wwf_score":6},{"word":"OBA","scrabble_score":5,"wwf_score":6},{"word":"OCA","scrabble_score":5,"wwf_score":6},{"word":"ODA","scrabble_score":4,"wwf_score":4},{"word":"OKA","scrabble_score":7,"wwf_score":7},{"word":"ORA","scrabble_score":3,"wwf_score":3},{"word":"OVA","scrabble_score":6,"wwf_score":7},{"word":"PEA","scrabble_score":5,"wwf_score":6},{"word":"PIA","scrabble_score":5,"wwf_score":6},{"word":"PYA","scrabble_score":8,"wwf_score":8},{"word":"QUA","scrabble_score":12,"wwf_score":13},{"word":"RIA","scrabble_score":3,"wwf_score":3},{"word":"RYA","scrabble_score":6,"wwf_score":5},{"word":"SEA","scrabble_score":3,"wwf_score":3},{"word":"SHA","scrabble_score":6,"wwf_score":5},{"word":"SKA","scrabble_score":7,"wwf_score":7},{"word":"SPA","scrabble_score":5,"wwf_score":6},{"word":"TEA","scrabble_score":3,"wwf_score":3},{"word":"TWA","scrabble_score":6,"wwf_score":6},{"word":"UTA","scrabble_score":3,"wwf_score":4},{"word":"VIA","scrabble_score":6,"wwf_score":7},{"word":"WHA","scrabble_score":9,"wwf_score":8},{"word":"YEA","scrabble_score":6,"wwf_score":5},{"word":"ZOA","scrabble_score":12,"wwf_score":12}],"4":[{"word":"ABBA","scrabble_score":8,"wwf_score":10},{"word":"ACTA","scrabble_score":6,"wwf_score":7},{"word":"AGHA","scrabble_score":8,"wwf_score":8},{"word":"AGMA","scrabble_score":7,"wwf_score":9},{"word":"ALBA","scrabble_score":6,"wwf_score":8},{"word":"ALFA","scrabble_score":7,"wwf_score":8},{"word":"ALGA","scrabble_score":5,"wwf_score":7},{"word":"ALMA","scrabble_score":6,"wwf_score":8},{"word":"AMIA","scrabble_score":6,"wwf_score":7},{"word":"ANGA","scrabble_score":5,"wwf_score":7},{"word":"ANNA","scrabble_score":4,"wwf_score":6},{"word":"ANOA","scrabble_score":4,"wwf_score":5},{"word":"ANSA","scrabble_score":4,"wwf_score":5},{"word":"ANTA","scrabble_score":4,"wwf_score":5},{"word":"AQUA","scrabble_score":13,"wwf_score":14},{"word":"AREA","scrabble_score":4,"wwf_score":4},{"word":"ARIA","scrabble_score":4,"wwf_score":4},{"word":"ASEA","scrabble_score":4,"wwf_score":4},{"word":"ATMA","scrabble_score":6,"wwf_score":7},{"word":"AURA","scrabble_score":4,"wwf_score":5},{"word":"BABA","scrabble_score":8,"wwf_score":10},{"word":"BEMA","scrabble_score":8,"wwf_score":10},{"word":"BETA","scrabble_score":6,"wwf_score":7},{"word":"BIMA","scrabble_score":8,"wwf_score":10},{"word":"BOLA","scrabble_score":6,"wwf_score":8},{"word":"BORA","scrabble_score":6,"wwf_score":7},{"word":"BOTA","scrabble_score":6,"wwf_score":7},{"word":"BUNA","scrabble_score":6,"wwf_score":9},{"word":"BURA","scrabble_score":6,"wwf_score":8},{"word":"CACA","scrabble_score":8,"wwf_score":10},{"word":"CASA","scrabble_score":6,"wwf_score":7},{"word":"CECA","scrabble_score":8,"wwf_score":10},{"word":"CHIA","scrabble_score":9,"wwf_score":9},{"word":"COCA","scrabble_score":8,"wwf_score":10},{"word":"CODA","scrabble_score":7,"wwf_score":8},{"word":"COLA","scrabble_score":6,"wwf_score":8},{"word":"COMA","scrabble_score":8,"wwf_score":10},{"word":"COXA","scrabble_score":13,"wwf_score":14},{"word":"CYMA","scrabble_score":11,"wwf_score":12},{"word":"DADA","scrabble_score":6,"wwf_score":6},{"word":"DATA","scrabble_score":5,"wwf_score":5},{"word":"DEVA","scrabble_score":8,"wwf_score":9},{"word":"DITA","scrabble_score":5,"wwf_score":5},{"word":"DIVA","scrabble_score":8,"wwf_score":9},{"word":"DONA","scrabble_score":5,"wwf_score":6},{"word":"DOPA","scrabble_score":7,"wwf_score":8},{"word":"DUMA","scrabble_score":7,"wwf_score":9},{"word":"DURA","scrabble_score":5,"wwf_score":6},{"word":"EPHA","scrabble_score":9,"wwf_score":9},{"word":"ETNA","scrabble_score":4,"wwf_score":5},{"word":"EYRA","scrabble_score":7,"wwf_score":6},{"word":"FAVA","scrabble_score":10,"wwf_score":11},{"word":"FETA","scrabble_score":7,"wwf_score":7},{"word":"FILA","scrabble_score":7,"wwf_score":8},{"word":"FLEA","scrabble_score":7,"wwf_score":8},{"word":"FORA","scrabble_score":7,"wwf_score":7},{"word":"GAGA","scrabble_score":6,"wwf_score":8},{"word":"GALA","scrabble_score":5,"wwf_score":7},{"word":"GAMA","scrabble_score":7,"wwf_score":9},{"word":"GETA","scrabble_score":5,"wwf_score":6},{"word":"GIGA","scrabble_score":6,"wwf_score":8},{"word":"GLIA","scrabble_score":5,"wwf_score":7},{"word":"HAHA","scrabble_score":10,"wwf_score":8},{"word":"HILA","scrabble_score":7,"wwf_score":7},{"word":"HORA","scrabble_score":7,"wwf_score":6},{"word":"HOYA","scrabble_score":10,"wwf_score":8},{"word":"HULA","scrabble_score":7,"wwf_score":8},{"word":"HYLA","scrabble_score":10,"wwf_score":9},{"word":"IDEA","scrabble_score":5,"wwf_score":5},{"word":"ILEA","scrabble_score":4,"wwf_score":5},{"word":"ILIA","scrabble_score":4,"wwf_score":5},{"word":"ILKA","scrabble_score":8,"wwf_score":9},{"word":"INIA","scrabble_score":4,"wwf_score":5},{"word":"IOTA","scrabble_score":4,"wwf_score":4},{"word":"ISBA","scrabble_score":6,"wwf_score":7},{"word":"IXIA","scrabble_score":11,"wwf_score":11},{"word":"JAVA","scrabble_score":14,"wwf_score":17},{"word":"JOTA","scrabble_score":11,"wwf_score":13},{"word":"JUBA","scrabble_score":13,"wwf_score":17},{"word":"JUGA","scrabble_score":12,"wwf_score":16},{"word":"JURA","scrabble_score":11,"wwf_score":14},{"word":"KAKA","scrabble_score":12,"wwf_score":12},{"word":"KANA","scrabble_score":8,"wwf_score":9},{"word":"KAPA","scrabble_score":10,"wwf_score":11},{"word":"KATA","scrabble_score":8,"wwf_score":8},{"word":"KAVA","scrabble_score":11,"wwf_score":12},{"word":"KINA","scrabble_score":8,"wwf_score":9},{"word":"KIVA","scrabble_score":11,"wwf_score":12},{"word":"KOLA","scrabble_score":8,"wwf_score":9},{"word":"KORA","scrabble_score":8,"wwf_score":8},{"word":"KUNA","scrabble_score":8,"wwf_score":10},{"word":"LAMA","scrabble_score":6,"wwf_score":8},{"word":"LAVA","scrabble_score":7,"wwf_score":9},{"word":"LEVA","scrabble_score":7,"wwf_score":9},{"word":"LIMA","scrabble_score":6,"wwf_score":8},{"word":"LIPA","scrabble_score":6,"wwf_score":8},{"word":"LIRA","scrabble_score":4,"wwf_score":5},{"word":"LOCA","scrabble_score":6,"wwf_score":8},{"word":"LOTA","scrabble_score":4,"wwf_score":5},{"word":"LUMA","scrabble_score":6,"wwf_score":9},{"word":"LUNA","scrabble_score":4,"wwf_score":7},{"word":"MAMA","scrabble_score":8,"wwf_score":10},{"word":"MANA","scrabble_score":6,"wwf_score":8},{"word":"MARA","scrabble_score":6,"wwf_score":7},{"word":"MASA","scrabble_score":6,"wwf_score":7},{"word":"MAYA","scrabble_score":9,"wwf_score":9},{"word":"MEGA","scrabble_score":7,"wwf_score":9},{"word":"MESA","scrabble_score":6,"wwf_score":7},{"word":"META","scrabble_score":6,"wwf_score":7},{"word":"MICA","scrabble_score":8,"wwf_score":10},{"word":"MINA","scrabble_score":6,"wwf_score":8},{"word":"MOLA","scrabble_score":6,"wwf_score":8},{"word":"MORA","scrabble_score":6,"wwf_score":7},{"word":"MOXA","scrabble_score":13,"wwf_score":14},{"word":"MURA","scrabble_score":6,"wwf_score":8},{"word":"MYNA","scrabble_score":9,"wwf_score":10},{"word":"NADA","scrabble_score":5,"wwf_score":6},{"word":"NALA","scrabble_score":4,"wwf_score":6},{"word":"NANA","scrabble_score":4,"wwf_score":6},{"word":"NAPA","scrabble_score":6,"wwf_score":8},{"word":"NEMA","scrabble_score":6,"wwf_score":8},{"word":"NIPA","scrabble_score":6,"wwf_score":8},{"word":"NOMA","scrabble_score":6,"wwf_score":8},{"word":"NONA","scrabble_score":4,"wwf_score":6},{"word":"NOTA","scrabble_score":4,"wwf_score":5},{"word":"NOVA","scrabble_score":7,"wwf_score":9},{"word":"OBIA","scrabble_score":6,"wwf_score":7},{"word":"ODEA","scrabble_score":5,"wwf_score":5},{"word":"OHIA","scrabble_score":7,"wwf_score":6},{"word":"OKRA","scrabble_score":8,"wwf_score":8},{"word":"OLEA","scrabble_score":4,"wwf_score":5},{"word":"OLLA","scrabble_score":4,"wwf_score":6},{"word":"ORCA","scrabble_score":6,"wwf_score":7},{"word":"ORRA","scrabble_score":4,"wwf_score":4},{"word":"OSSA","scrabble_score":4,"wwf_score":4},{"word":"PACA","scrabble_score":8,"wwf_score":10},{"word":"PAPA","scrabble_score":8,"wwf_score":10},{"word":"PARA","scrabble_score":6,"wwf_score":7},{"word":"PICA","scrabble_score":8,"wwf_score":10},{"word":"PIKA","scrabble_score":10,"wwf_score":11},{"word":"PIMA","scrabble_score":8,"wwf_score":10},{"word":"PINA","scrabble_score":6,"wwf_score":8},{"word":"PITA","scrabble_score":6,"wwf_score":7},{"word":"PLEA","scrabble_score":6,"wwf_score":8},{"word":"PROA","scrabble_score":6,"wwf_score":7},{"word":"PUJA","scrabble_score":13,"wwf_score":17},{"word":"PULA","scrabble_score":6,"wwf_score":9},{"word":"PUMA","scrabble_score":8,"wwf_score":11},{"word":"PUNA","scrabble_score":6,"wwf_score":9},{"word":"PUPA","scrabble_score":8,"wwf_score":11},{"word":"RAGA","scrabble_score":5,"wwf_score":6},{"word":"RAIA","scrabble_score":4,"wwf_score":4},{"word":"RAJA","scrabble_score":11,"wwf_score":13},{"word":"RAYA","scrabble_score":7,"wwf_score":6},{"word":"RHEA","scrabble_score":7,"wwf_score":6},{"word":"ROTA","scrabble_score":4,"wwf_score":4},{"word":"RUGA","scrabble_score":5,"wwf_score":7},{"word":"SAGA","scrabble_score":5,"wwf_score":6},{"word":"SERA","scrabble_score":4,"wwf_score":4},{"word":"SETA","scrabble_score":4,"wwf_score":4},{"word":"SHEA","scrabble_score":7,"wwf_score":6},{"word":"SHWA","scrabble_score":10,"wwf_score":9},{"word":"SIKA","scrabble_score":8,"wwf_score":8},{"word":"SIMA","scrabble_score":6,"wwf_score":7},{"word":"SKUA","scrabble_score":8,"wwf_score":9},{"word":"SOBA","scrabble_score":6,"wwf_score":7},{"word":"SOCA","scrabble_score":6,"wwf_score":7},{"word":"SODA","scrabble_score":5,"wwf_score":5},{"word":"SOFA","scrabble_score":7,"wwf_score":7},{"word":"SOJA","scrabble_score":11,"wwf_score":13},{"word":"SOLA","scrabble_score":4,"wwf_score":5},{"word":"SOMA","scrabble_score":6,"wwf_score":7},{"word":"SORA","scrabble_score":4,"wwf_score":4},{"word":"SOYA","scrabble_score":7,"wwf_score":6},{"word":"STOA","scrabble_score":4,"wwf_score":4},{"word":"SUBA","scrabble_score":6,"wwf_score":8},{"word":"SURA","scrabble_score":4,"wwf_score":5},{"word":"TAKA","scrabble_score":8,"wwf_score":8},{"word":"TALA","scrabble_score":4,"wwf_score":5},{"word":"TAPA","scrabble_score":6,"wwf_score":7},{"word":"TAXA","scrabble_score":11,"wwf_score":11},{"word":"TELA","scrabble_score":4,"wwf_score":5},{"word":"TEPA","scrabble_score":6,"wwf_score":7},{"word":"TOEA","scrabble_score":4,"wwf_score":4},{"word":"TOGA","scrabble_score":5,"wwf_score":6},{"word":"TOLA","scrabble_score":4,"wwf_score":5},{"word":"TORA","scrabble_score":4,"wwf_score":4},{"word":"TUBA","scrabble_score":6,"wwf_score":8},{"word":"TUFA","scrabble_score":7,"wwf_score":8},{"word":"TUNA","scrabble_score":4,"wwf_score":6},{"word":"ULNA","scrabble_score":4,"wwf_score":7},{"word":"ULVA","scrabble_score":7,"wwf_score":10},{"word":"UREA","scrabble_score":4,"wwf_score":5},{"word":"URSA","scrabble_score":4,"wwf_score":5},{"word":"UVEA","scrabble_score":7,"wwf_score":9},{"word":"VARA","scrabble_score":7,"wwf_score":8},{"word":"VASA","scrabble_score":7,"wwf_score":8},{"word":"VELA","scrabble_score":7,"wwf_score":9},{"word":"VENA","scrabble_score":7,"wwf_score":9},{"word":"VERA","scrabble_score":7,"wwf_score":8},{"word":"VIGA","scrabble_score":8,"wwf_score":10},{"word":"VINA","scrabble_score":7,"wwf_score":9},{"word":"VISA","scrabble_score":7,"wwf_score":8},{"word":"VITA","scrabble_score":7,"wwf_score":8},{"word":"VIVA","scrabble_score":10,"wwf_score":12},{"word":"WEKA","scrabble_score":11,"wwf_score":11},{"word":"WHOA","scrabble_score":10,"wwf_score":9},{"word":"YOGA","scrabble_score":8,"wwf_score":8},{"word":"YUCA","scrabble_score":9,"wwf_score":10},{"word":"YUGA","scrabble_score":8,"wwf_score":9},{"word":"ZETA","scrabble_score":13,"wwf_score":13},{"word":"ZOEA","scrabble_score":13,"wwf_score":13},{"word":"ZONA","scrabble_score":13,"wwf_score":14}],"5":[{"word":"ABACA","scrabble_score":9,"wwf_score":11},{"word":"ABAKA","scrabble_score":11,"wwf_score":12},{"word":"ABAYA","scrabble_score":10,"wwf_score":10},{"word":"ABOMA","scrabble_score":9,"wwf_score":11},{"word":"ACETA","scrabble_score":7,"wwf_score":8},{"word":"ADYTA","scrabble_score":9,"wwf_score":8},{"word":"AECIA","scrabble_score":7,"wwf_score":8},{"word":"AGAMA","scrabble_score":8,"wwf_score":10},{"word":"AGITA","scrabble_score":6,"wwf_score":7},{"word":"AGORA","scrabble_score":6,"wwf_score":7},{"word":"AGRIA","scrabble_score":6,"wwf_score":7},{"word":"AJIVA","scrabble_score":15,"wwf_score":18},{"word":"AJUGA","scrabble_score":13,"wwf_score":17},{"word":"AKELA","scrabble_score":9,"wwf_score":10},{"word":"ALIYA","scrabble_score":8,"wwf_score":8},{"word":"ALOHA","scrabble_score":8,"wwf_score":8},{"word":"ALPHA","scrabble_score":10,"wwf_score":11},{"word":"ALULA","scrabble_score":5,"wwf_score":8},{"word":"AMEBA","scrabble_score":9,"wwf_score":11},{"word":"AMIGA","scrabble_score":8,"wwf_score":10},{"word":"AMNIA","scrabble_score":7,"wwf_score":9},{"word":"ANIMA","scrabble_score":7,"wwf_score":9},{"word":"ANTRA","scrabble_score":5,"wwf_score":6},{"word":"AORTA","scrabble_score":5,"wwf_score":5},{"word":"APNEA","scrabble_score":7,"wwf_score":9},{"word":"ARECA","scrabble_score":7,"wwf_score":8},{"word":"ARENA","scrabble_score":5,"wwf_score":6},{"word":"AREPA","scrabble_score":7,"wwf_score":8},{"word":"AROMA","scrabble_score":7,"wwf_score":8},{"word":"ASANA","scrabble_score":5,"wwf_score":6},{"word":"ASYLA","scrabble_score":8,"wwf_score":8},{"word":"ATRIA","scrabble_score":5,"wwf_score":5},{"word":"BABKA","scrabble_score":13,"wwf_score":15},{"word":"BACCA","scrabble_score":11,"wwf_score":14},{"word":"BAIZA","scrabble_score":16,"wwf_score":17},{"word":"BALSA","scrabble_score":7,"wwf_score":9},{"word":"BANDA","scrabble_score":8,"wwf_score":10},{"word":"BARCA","scrabble_score":9,"wwf_score":11},{"word":"BELGA","scrabble_score":8,"wwf_score":11},{"word":"BETTA","scrabble_score":7,"wwf_score":8},{"word":"BIOTA","scrabble_score":7,"wwf_score":8},{"word":"BOHEA","scrabble_score":10,"wwf_score":10},{"word":"BOYLA","scrabble_score":10,"wwf_score":11},{"word":"BRAVA","scrabble_score":10,"wwf_score":12},{"word":"BRAZA","scrabble_score":16,"wwf_score":17},{"word":"BULLA","scrabble_score":7,"wwf_score":11},{"word":"BUNYA","scrabble_score":10,"wwf_score":12},{"word":"BURKA","scrabble_score":11,"wwf_score":13},{"word":"BURQA","scrabble_score":16,"wwf_score":18},{"word":"BURSA","scrabble_score":7,"wwf_score":9},{"word":"BWANA","scrabble_score":10,"wwf_score":12},{"word":"CAECA","scrabble_score":9,"wwf_score":11},{"word":"CALLA","scrabble_score":7,"wwf_score":10},{"word":"CANNA","scrabble_score":7,"wwf_score":10},{"word":"CEIBA","scrabble_score":9,"wwf_score":11},{"word":"CELLA","scrabble_score":7,"wwf_score":10},{"word":"CERIA","scrabble_score":7,"wwf_score":8},{"word":"CESTA","scrabble_score":7,"wwf_score":8},{"word":"CHELA","scrabble_score":10,"wwf_score":11},{"word":"CHICA","scrabble_score":12,"wwf_score":13},{"word":"CHINA","scrabble_score":10,"wwf_score":11},{"word":"CHOLA","scrabble_score":10,"wwf_score":11},{"word":"CHUFA","scrabble_score":13,"wwf_score":14},{"word":"CILIA","scrabble_score":7,"wwf_score":9},{"word":"CIRCA","scrabble_score":9,"wwf_score":11},{"word":"CNIDA","scrabble_score":8,"wwf_score":10},{"word":"COALA","scrabble_score":7,"wwf_score":9},{"word":"COBIA","scrabble_score":9,"wwf_score":11},{"word":"COBRA","scrabble_score":9,"wwf_score":11},{"word":"COCOA","scrabble_score":9,"wwf_score":11},{"word":"COLZA","scrabble_score":16,"wwf_score":18},{"word":"COMMA","scrabble_score":11,"wwf_score":14},{"word":"CONGA","scrabble_score":8,"wwf_score":11},{"word":"COPRA","scrabble_score":9,"wwf_score":11},{"word":"CORIA","scrabble_score":7,"wwf_score":8},{"word":"COSTA","scrabble_score":7,"wwf_score":8},{"word":"COTTA","scrabble_score":7,"wwf_score":8},{"word":"CRURA","scrabble_score":7,"wwf_score":9},{"word":"CULPA","scrabble_score":9,"wwf_score":13},{"word":"CUPPA","scrabble_score":11,"wwf_score":15},{"word":"CURIA","scrabble_score":7,"wwf_score":9},{"word":"DACHA","scrabble_score":11,"wwf_score":11},{"word":"DAGGA","scrabble_score":8,"wwf_score":10},{"word":"DELTA","scrabble_score":6,"wwf_score":7},{"word":"DERMA","scrabble_score":8,"wwf_score":9},{"word":"DICTA","scrabble_score":8,"wwf_score":9},{"word":"DOBLA","scrabble_score":8,"wwf_score":10},{"word":"DOBRA","scrabble_score":8,"wwf_score":9},{"word":"DOGMA","scrabble_score":9,"wwf_score":11},{"word":"DOLMA","scrabble_score":8,"wwf_score":10},{"word":"DONGA","scrabble_score":7,"wwf_score":9},{"word":"DONNA","scrabble_score":6,"wwf_score":8},{"word":"DORSA","scrabble_score":6,"wwf_score":6},{"word":"DOULA","scrabble_score":6,"wwf_score":8},{"word":"DOUMA","scrabble_score":8,"wwf_score":10},{"word":"DOURA","scrabble_score":6,"wwf_score":7},{"word":"DRAMA","scrabble_score":8,"wwf_score":9},{"word":"DULIA","scrabble_score":6,"wwf_score":8},{"word":"DUMKA","scrabble_score":12,"wwf_score":14},{"word":"DURRA","scrabble_score":6,"wwf_score":7},{"word":"EDEMA","scrabble_score":8,"wwf_score":9},{"word":"ENEMA","scrabble_score":7,"wwf_score":9},{"word":"ENTIA","scrabble_score":5,"wwf_score":6},{"word":"ERICA","scrabble_score":7,"wwf_score":8},{"word":"ETYMA","scrabble_score":10,"wwf_score":10},{"word":"EXTRA","scrabble_score":12,"wwf_score":12},{"word":"FACIA","scrabble_score":10,"wwf_score":11},{"word":"FAENA","scrabble_score":8,"wwf_score":9},{"word":"FANGA","scrabble_score":9,"wwf_score":11},{"word":"FATWA","scrabble_score":11,"wwf_score":11},{"word":"FAUNA","scrabble_score":8,"wwf_score":10},{"word":"FELLA","scrabble_score":8,"wwf_score":10},{"word":"FERIA","scrabble_score":8,"wwf_score":8},{"word":"FINCA","scrabble_score":10,"wwf_score":12},{"word":"FLORA","scrabble_score":8,"wwf_score":9},{"word":"FLOTA","scrabble_score":8,"wwf_score":9},{"word":"FOLIA","scrabble_score":8,"wwf_score":9},{"word":"FOSSA","scrabble_score":8,"wwf_score":8},{"word":"FOVEA","scrabble_score":11,"wwf_score":12},{"word":"FRENA","scrabble_score":8,"wwf_score":9},{"word":"GALEA","scrabble_score":6,"wwf_score":8},{"word":"GAMBA","scrabble_score":10,"wwf_score":13},{"word":"GAMMA","scrabble_score":10,"wwf_score":13},{"word":"GANJA","scrabble_score":13,"wwf_score":17},{"word":"GARDA","scrabble_score":7,"wwf_score":8},{"word":"GEMMA","scrabble_score":10,"wwf_score":13},{"word":"GENOA","scrabble_score":6,"wwf_score":8},{"word":"GENUA","scrabble_score":6,"wwf_score":9},{"word":"GLEBA","scrabble_score":8,"wwf_score":11},{"word":"GONIA","scrabble_score":6,"wwf_score":8},{"word":"GRAMA","scrabble_score":8,"wwf_score":10},{"word":"GRANA","scrabble_score":6,"wwf_score":8},{"word":"GUAVA","scrabble_score":9,"wwf_score":12},{"word":"GUMMA","scrabble_score":10,"wwf_score":14},{"word":"GUTTA","scrabble_score":6,"wwf_score":8},{"word":"GYOZA","scrabble_score":18,"wwf_score":18},{"word":"HAIKA","scrabble_score":12,"wwf_score":11},{"word":"HALMA","scrabble_score":10,"wwf_score":11},{"word":"HALVA","scrabble_score":11,"wwf_score":12},{"word":"HAMZA","scrabble_score":19,"wwf_score":19},{"word":"HANSA","scrabble_score":8,"wwf_score":8},{"word":"HENNA","scrabble_score":8,"wwf_score":9},{"word":"HERMA","scrabble_score":10,"wwf_score":10},{"word":"HIJRA","scrabble_score":15,"wwf_score":16},{"word":"HOLLA","scrabble_score":8,"wwf_score":9},{"word":"HONDA","scrabble_score":9,"wwf_score":9},{"word":"HOOKA","scrabble_score":12,"wwf_score":11},{"word":"HOSTA","scrabble_score":8,"wwf_score":7},{"word":"HUZZA","scrabble_score":26,"wwf_score":26},{"word":"HYDRA","scrabble_score":12,"wwf_score":10},{"word":"HYENA","scrabble_score":11,"wwf_score":10},{"word":"HYPHA","scrabble_score":16,"wwf_score":14},{"word":"INFRA","scrabble_score":8,"wwf_score":9},{"word":"IXORA","scrabble_score":12,"wwf_score":12},{"word":"JAGRA","scrabble_score":13,"wwf_score":16},{"word":"JNANA","scrabble_score":12,"wwf_score":16},{"word":"JUNTA","scrabble_score":12,"wwf_score":16},{"word":"KALPA","scrabble_score":11,"wwf_score":13},{"word":"KAPPA","scrabble_score":13,"wwf_score":15},{"word":"KARMA","scrabble_score":11,"wwf_score":12},{"word":"KASHA","scrabble_score":12,"wwf_score":11},{"word":"KHEDA","scrabble_score":13,"wwf_score":12},{"word":"KIBLA","scrabble_score":11,"wwf_score":13},{"word":"KOALA","scrabble_score":9,"wwf_score":10},{"word":"KOPPA","scrabble_score":13,"wwf_score":15},{"word":"KORMA","scrabble_score":11,"wwf_score":12},{"word":"KRONA","scrabble_score":9,"wwf_score":10},{"word":"KURTA","scrabble_score":9,"wwf_score":10},{"word":"LABIA","scrabble_score":7,"wwf_score":9},{"word":"LABRA","scrabble_score":7,"wwf_score":9},{"word":"LAMIA","scrabble_score":7,"wwf_score":9},{"word":"LARVA","scrabble_score":8,"wwf_score":10},{"word":"LAURA","scrabble_score":5,"wwf_score":7},{"word":"LEHUA","scrabble_score":8,"wwf_score":9},{"word":"LEMMA","scrabble_score":9,"wwf_score":12},{"word":"LEPTA","scrabble_score":7,"wwf_score":9},{"word":"LIANA","scrabble_score":5,"wwf_score":7},{"word":"LIBRA","scrabble_score":7,"wwf_score":9},{"word":"LIMBA","scrabble_score":9,"wwf_score":12},{"word":"LIMPA","scrabble_score":9,"wwf_score":12},{"word":"LINGA","scrabble_score":6,"wwf_score":9},{"word":"LLAMA","scrabble_score":7,"wwf_score":10},{"word":"LOGIA","scrabble_score":6,"wwf_score":8},{"word":"LOOFA","scrabble_score":8,"wwf_score":9},{"word":"LOUMA","scrabble_score":7,"wwf_score":10},{"word":"LUFFA","scrabble_score":11,"wwf_score":13},{"word":"LUTEA","scrabble_score":5,"wwf_score":7},{"word":"LYCEA","scrabble_score":10,"wwf_score":11},{"word":"LYCRA","scrabble_score":10,"wwf_score":11},{"word":"LYSSA","scrabble_score":8,"wwf_score":8},{"word":"LYTTA","scrabble_score":8,"wwf_score":8},{"word":"MAFIA","scrabble_score":10,"wwf_score":11},{"word":"MAGMA","scrabble_score":10,"wwf_score":13},{"word":"MAMBA","scrabble_score":11,"wwf_score":14},{"word":"MAMMA","scrabble_score":11,"wwf_score":14},{"word":"MANGA","scrabble_score":8,"wwf_score":11},{"word":"MANIA","scrabble_score":7,"wwf_score":9},{"word":"MANNA","scrabble_score":7,"wwf_score":10},{"word":"MANTA","scrabble_score":7,"wwf_score":9},{"word":"MARIA","scrabble_score":7,"wwf_score":8},{"word":"MARKA","scrabble_score":11,"wwf_score":12},{"word":"MASSA","scrabble_score":7,"wwf_score":8},{"word":"MATZA","scrabble_score":16,"wwf_score":17},{"word":"MBIRA","scrabble_score":9,"wwf_score":11},{"word":"MECCA","scrabble_score":11,"wwf_score":14},{"word":"MEDIA","scrabble_score":8,"wwf_score":9},{"word":"MENSA","scrabble_score":7,"wwf_score":9},{"word":"MENTA","scrabble_score":7,"wwf_score":9},{"word":"MICRA","scrabble_score":9,"wwf_score":11},{"word":"MIKRA","scrabble_score":11,"wwf_score":12},{"word":"MILIA","scrabble_score":7,"wwf_score":9},{"word":"MILPA","scrabble_score":9,"wwf_score":12},{"word":"MIRZA","scrabble_score":16,"wwf_score":17},{"word":"MOCHA","scrabble_score":12,"wwf_score":13},{"word":"MOIRA","scrabble_score":7,"wwf_score":8},{"word":"MOMMA","scrabble_score":11,"wwf_score":14},{"word":"MOOLA","scrabble_score":7,"wwf_score":9},{"word":"MUDRA","scrabble_score":8,"wwf_score":10},{"word":"MULLA","scrabble_score":7,"wwf_score":11},{"word":"MURRA","scrabble_score":7,"wwf_score":9},{"word":"MUSCA","scrabble_score":9,"wwf_score":12},{"word":"MYOMA","scrabble_score":12,"wwf_score":13},{"word":"NAIRA","scrabble_score":5,"wwf_score":6},{"word":"NAKFA","scrabble_score":12,"wwf_score":13},{"word":"NAPPA","scrabble_score":9,"wwf_score":12},{"word":"NINJA","scrabble_score":12,"wwf_score":16},{"word":"NORIA","scrabble_score":5,"wwf_score":6},{"word":"NUBIA","scrabble_score":7,"wwf_score":10},{"word":"NUCHA","scrabble_score":10,"wwf_score":12},{"word":"NYALA","scrabble_score":8,"wwf_score":9},{"word":"OCREA","scrabble_score":7,"wwf_score":8},{"word":"OIDIA","scrabble_score":6,"wwf_score":6},{"word":"OMASA","scrabble_score":7,"wwf_score":8},{"word":"OMEGA","scrabble_score":8,"wwf_score":10},{"word":"OPERA","scrabble_score":7,"wwf_score":8},{"word":"OSSIA","scrabble_score":5,"wwf_score":5},{"word":"OSTIA","scrabble_score":5,"wwf_score":5},{"word":"PACHA","scrabble_score":12,"wwf_score":13},{"word":"PAISA","scrabble_score":7,"wwf_score":8},{"word":"PALEA","scrabble_score":7,"wwf_score":9},{"word":"PAMPA","scrabble_score":11,"wwf_score":14},{"word":"PANDA","scrabble_score":8,"wwf_score":10},{"word":"PANGA","scrabble_score":8,"wwf_score":11},{"word":"PARKA","scrabble_score":11,"wwf_score":12},{"word":"PASHA","scrabble_score":10,"wwf_score":10},{"word":"PASTA","scrabble_score":7,"wwf_score":8},{"word":"PENNA","scrabble_score":7,"wwf_score":10},{"word":"PEPLA","scrabble_score":9,"wwf_score":12},{"word":"PEREA","scrabble_score":7,"wwf_score":8},{"word":"PHYLA","scrabble_score":13,"wwf_score":13},{"word":"PIETA","scrabble_score":7,"wwf_score":8},{"word":"PILEA","scrabble_score":7,"wwf_score":9},{"word":"PINNA","scrabble_score":7,"wwf_score":10},{"word":"PINTA","scrabble_score":7,"wwf_score":9},{"word":"PITTA","scrabble_score":7,"wwf_score":8},{"word":"PIZZA","scrabble_score":25,"wwf_score":26},{"word":"PLAYA","scrabble_score":10,"wwf_score":11},{"word":"PLAZA","scrabble_score":16,"wwf_score":18},{"word":"PLENA","scrabble_score":7,"wwf_score":10},{"word":"PLICA","scrabble_score":9,"wwf_score":12},{"word":"PODIA","scrabble_score":8,"wwf_score":9},{"word":"POLKA","scrabble_score":11,"wwf_score":13},{"word":"POPPA","scrabble_score":11,"wwf_score":14},{"word":"PRESA","scrabble_score":7,"wwf_score":8},{"word":"PRIMA","scrabble_score":9,"wwf_score":11},{"word":"PRUTA","scrabble_score":7,"wwf_score":9},{"word":"PUCKA","scrabble_score":13,"wwf_score":16},{"word":"PUKKA","scrabble_score":15,"wwf_score":17},{"word":"PUNKA","scrabble_score":11,"wwf_score":14},{"word":"PURDA","scrabble_score":8,"wwf_score":10},{"word":"QUOTA","scrabble_score":14,"wwf_score":15},{"word":"RAITA","scrabble_score":5,"wwf_score":5},{"word":"REATA","scrabble_score":5,"wwf_score":5},{"word":"RECTA","scrabble_score":7,"wwf_score":8},{"word":"REDIA","scrabble_score":6,"wwf_score":6},{"word":"REGMA","scrabble_score":8,"wwf_score":10},{"word":"REGNA","scrabble_score":6,"wwf_score":8},{"word":"RETIA","scrabble_score":5,"wwf_score":5},{"word":"RHYTA","scrabble_score":11,"wwf_score":9},{"word":"RIATA","scrabble_score":5,"wwf_score":5},{"word":"RIOJA","scrabble_score":12,"wwf_score":14},{"word":"RUANA","scrabble_score":5,"wwf_score":7},{"word":"RUMBA","scrabble_score":9,"wwf_score":12},{"word":"SABRA","scrabble_score":7,"wwf_score":8},{"word":"SACRA","scrabble_score":7,"wwf_score":8},{"word":"SAIGA","scrabble_score":6,"wwf_score":7},{"word":"SALPA","scrabble_score":7,"wwf_score":9},{"word":"SALSA","scrabble_score":5,"wwf_score":6},{"word":"SAMBA","scrabble_score":9,"wwf_score":11},{"word":"SANGA","scrabble_score":6,"wwf_score":8},{"word":"SAUNA","scrabble_score":5,"wwf_score":7},{"word":"SCENA","scrabble_score":7,"wwf_score":9},{"word":"SCHWA","scrabble_score":13,"wwf_score":13},{"word":"SCUBA","scrabble_score":9,"wwf_score":12},{"word":"SCUTA","scrabble_score":7,"wwf_score":9},{"word":"SELVA","scrabble_score":8,"wwf_score":10},{"word":"SENNA","scrabble_score":5,"wwf_score":7},{"word":"SENSA","scrabble_score":5,"wwf_score":6},{"word":"SEPIA","scrabble_score":7,"wwf_score":8},{"word":"SEPTA","scrabble_score":7,"wwf_score":8},{"word":"SHIVA","scrabble_score":11,"wwf_score":11},{"word":"SIGLA","scrabble_score":6,"wwf_score":8},{"word":"SIGMA","scrabble_score":8,"wwf_score":10},{"word":"SIGNA","scrabble_score":6,"wwf_score":8},{"word":"SILVA","scrabble_score":8,"wwf_score":10},{"word":"SIRRA","scrabble_score":5,"wwf_score":5},{"word":"SOFTA","scrabble_score":8,"wwf_score":8},{"word":"SORTA","scrabble_score":5,"wwf_score":5},{"word":"SPICA","scrabble_score":9,"wwf_score":11},{"word":"SPUTA","scrabble_score":7,"wwf_score":9},{"word":"STELA","scrabble_score":5,"wwf_score":6},{"word":"STOMA","scrabble_score":7,"wwf_score":8},{"word":"STRIA","scrabble_score":5,"wwf_score":5},{"word":"STUPA","scrabble_score":7,"wwf_score":9},{"word":"SULFA","scrabble_score":8,"wwf_score":10},{"word":"SUMMA","scrabble_score":9,"wwf_score":12},{"word":"SUNNA","scrabble_score":5,"wwf_score":8},{"word":"SUPRA","scrabble_score":7,"wwf_score":9},{"word":"SURRA","scrabble_score":5,"wwf_score":6},{"word":"SUTRA","scrabble_score":5,"wwf_score":6},{"word":"SUTTA","scrabble_score":5,"wwf_score":6},{"word":"SYLVA","scrabble_score":11,"wwf_score":12},{"word":"TABLA","scrabble_score":7,"wwf_score":9},{"word":"TAFIA","scrabble_score":8,"wwf_score":8},{"word":"TAIGA","scrabble_score":6,"wwf_score":7},{"word":"TANGA","scrabble_score":6,"wwf_score":8},{"word":"TANKA","scrabble_score":9,"wwf_score":10},{"word":"TAZZA","scrabble_score":23,"wwf_score":23},{"word":"TECTA","scrabble_score":7,"wwf_score":8},{"word":"TEGUA","scrabble_score":6,"wwf_score":8},{"word":"TELIA","scrabble_score":5,"wwf_score":6},{"word":"TENIA","scrabble_score":5,"wwf_score":6},{"word":"TERGA","scrabble_score":6,"wwf_score":7},{"word":"TERRA","scrabble_score":5,"wwf_score":5},{"word":"TESLA","scrabble_score":5,"wwf_score":6},{"word":"TESTA","scrabble_score":5,"wwf_score":5},{"word":"TETRA","scrabble_score":5,"wwf_score":5},{"word":"THECA","scrabble_score":10,"wwf_score":10},{"word":"THETA","scrabble_score":8,"wwf_score":7},{"word":"THUJA","scrabble_score":15,"wwf_score":17},{"word":"THUYA","scrabble_score":11,"wwf_score":10},{"word":"TIARA","scrabble_score":5,"wwf_score":5},{"word":"TIBIA","scrabble_score":7,"wwf_score":8},{"word":"TIKKA","scrabble_score":13,"wwf_score":13},{"word":"TINEA","scrabble_score":5,"wwf_score":6},{"word":"TONGA","scrabble_score":6,"wwf_score":8},{"word":"TORTA","scrabble_score":5,"wwf_score":5},{"word":"TRONA","scrabble_score":5,"wwf_score":6},{"word":"TRYMA","scrabble_score":10,"wwf_score":10},{"word":"TSUBA","scrabble_score":7,"wwf_score":9},{"word":"ULAMA","scrabble_score":7,"wwf_score":10},{"word":"ULEMA","scrabble_score":7,"wwf_score":10},{"word":"ULTRA","scrabble_score":5,"wwf_score":7},{"word":"UMBRA","scrabble_score":9,"wwf_score":12},{"word":"UNCIA","scrabble_score":7,"wwf_score":10},{"word":"URBIA","scrabble_score":7,"wwf_score":9},{"word":"USNEA","scrabble_score":5,"wwf_score":7},{"word":"UVULA","scrabble_score":8,"wwf_score":12},{"word":"VACUA","scrabble_score":10,"wwf_score":13},{"word":"VANDA","scrabble_score":9,"wwf_score":11},{"word":"VARIA","scrabble_score":8,"wwf_score":9},{"word":"VARNA","scrabble_score":8,"wwf_score":10},{"word":"VEENA","scrabble_score":8,"wwf_score":10},{"word":"VESTA","scrabble_score":8,"wwf_score":9},{"word":"VIGIA","scrabble_score":9,"wwf_score":11},{"word":"VILLA","scrabble_score":8,"wwf_score":11},{"word":"VINCA","scrabble_score":10,"wwf_score":13},{"word":"VIOLA","scrabble_score":8,"wwf_score":10},{"word":"VIRGA","scrabble_score":9,"wwf_score":11},{"word":"VISTA","scrabble_score":8,"wwf_score":9},{"word":"VITTA","scrabble_score":8,"wwf_score":9},{"word":"VODKA","scrabble_score":13,"wwf_score":14},{"word":"VOILA","scrabble_score":8,"wwf_score":10},{"word":"VOLTA","scrabble_score":8,"wwf_score":10},{"word":"VOLVA","scrabble_score":11,"wwf_score":14},{"word":"VULVA","scrabble_score":11,"wwf_score":15},{"word":"WALLA","scrabble_score":8,"wwf_score":10},{"word":"WICCA","scrabble_score":12,"wwf_score":14},{"word":"WIRRA","scrabble_score":8,"wwf_score":8},{"word":"WISHA","scrabble_score":11,"wwf_score":10},{"word":"XENIA","scrabble_score":12,"wwf_score":13},{"word":"YENTA","scrabble_score":8,"wwf_score":8},{"word":"YERBA","scrabble_score":10,"wwf_score":10},{"word":"YUCCA","scrabble_score":12,"wwf_score":14},{"word":"YURTA","scrabble_score":8,"wwf_score":8},{"word":"ZAMIA","scrabble_score":16,"wwf_score":17},{"word":"ZANZA","scrabble_score":23,"wwf_score":24},{"word":"ZEBRA","scrabble_score":16,"wwf_score":17}],"6":[{"word":"ABASIA","scrabble_score":8,"wwf_score":9},{"word":"ABELIA","scrabble_score":8,"wwf_score":10},{"word":"ABOLLA","scrabble_score":8,"wwf_score":11},{"word":"ABULIA","scrabble_score":8,"wwf_score":11},{"word":"ACACIA","scrabble_score":10,"wwf_score":12},{"word":"ACEDIA","scrabble_score":9,"wwf_score":10},{"word":"ADNEXA","scrabble_score":14,"wwf_score":15},{"word":"AFTOSA","scrabble_score":9,"wwf_score":9},{"word":"AGENDA","scrabble_score":8,"wwf_score":10},{"word":"AGGADA","scrabble_score":9,"wwf_score":11},{"word":"AHIMSA","scrabble_score":11,"wwf_score":11},{"word":"ALASKA","scrabble_score":10,"wwf_score":11},{"word":"ALBATA","scrabble_score":8,"wwf_score":10},{"word":"ALEXIA","scrabble_score":13,"wwf_score":14},{"word":"ALODIA","scrabble_score":7,"wwf_score":8},{"word":"ALPACA","scrabble_score":10,"wwf_score":13},{"word":"ALTHEA","scrabble_score":9,"wwf_score":9},{"word":"ALUMNA","scrabble_score":8,"wwf_score":12},{"word":"AMARNA","scrabble_score":8,"wwf_score":10},{"word":"AMOEBA","scrabble_score":10,"wwf_score":12},{"word":"AMRITA","scrabble_score":8,"wwf_score":9},{"word":"AMUSIA","scrabble_score":8,"wwf_score":10},{"word":"ANEMIA","scrabble_score":8,"wwf_score":10},{"word":"ANGINA","scrabble_score":7,"wwf_score":10},{"word":"ANGORA","scrabble_score":7,"wwf_score":9},{"word":"ANNONA","scrabble_score":6,"wwf_score":9},{"word":"ANOPIA","scrabble_score":8,"wwf_score":10},{"word":"ANOXIA","scrabble_score":13,"wwf_score":14},{"word":"ANURIA","scrabble_score":6,"wwf_score":8},{"word":"APHTHA","scrabble_score":14,"wwf_score":13},{"word":"APNOEA","scrabble_score":8,"wwf_score":10},{"word":"APORIA","scrabble_score":8,"wwf_score":9},{"word":"ARCANA","scrabble_score":8,"wwf_score":10},{"word":"AREOLA","scrabble_score":6,"wwf_score":7},{"word":"ARGALA","scrabble_score":7,"wwf_score":9},{"word":"ARISTA","scrabble_score":6,"wwf_score":6},{"word":"ARMADA","scrabble_score":9,"wwf_score":10},{"word":"ARNICA","scrabble_score":8,"wwf_score":10},{"word":"ARRIBA","scrabble_score":8,"wwf_score":9},{"word":"ARROBA","scrabble_score":8,"wwf_score":9},{"word":"ASRAMA","scrabble_score":8,"wwf_score":9},{"word":"ASTHMA","scrabble_score":11,"wwf_score":11},{"word":"ATAXIA","scrabble_score":13,"wwf_score":13},{"word":"ATONIA","scrabble_score":6,"wwf_score":7},{"word":"AUCUBA","scrabble_score":10,"wwf_score":14},{"word":"AURORA","scrabble_score":6,"wwf_score":7},{"word":"AXILLA","scrabble_score":13,"wwf_score":15},{"word":"AZALEA","scrabble_score":15,"wwf_score":16},{"word":"BACULA","scrabble_score":10,"wwf_score":14},{"word":"BALATA","scrabble_score":8,"wwf_score":10},{"word":"BALBOA","scrabble_score":10,"wwf_score":13},{"word":"BANANA","scrabble_score":8,"wwf_score":11},{"word":"BARYTA","scrabble_score":11,"wwf_score":11},{"word":"BEFLEA","scrabble_score":11,"wwf_score":13},{"word":"BELUGA","scrabble_score":9,"wwf_score":13},{"word":"BEMATA","scrabble_score":10,"wwf_score":12},{"word":"BERTHA","scrabble_score":11,"wwf_score":11},{"word":"BHAKTA","scrabble_score":15,"wwf_score":15},{"word":"BILBOA","scrabble_score":10,"wwf_score":13},{"word":"BOCCIA","scrabble_score":12,"wwf_score":15},{"word":"BODEGA","scrabble_score":10,"wwf_score":12},{"word":"BONITA","scrabble_score":8,"wwf_score":10},{"word":"BRAHMA","scrabble_score":13,"wwf_score":14},{"word":"BREGMA","scrabble_score":11,"wwf_score":14},{"word":"BUDDHA","scrabble_score":13,"wwf_score":14},{"word":"BUGSHA","scrabble_score":12,"wwf_score":14},{"word":"BUQSHA","scrabble_score":20,"wwf_score":21},{"word":"BUSHWA","scrabble_score":14,"wwf_score":15},{"word":"CABALA","scrabble_score":10,"wwf_score":13},{"word":"CABANA","scrabble_score":10,"wwf_score":13},{"word":"CAEOMA","scrabble_score":10,"wwf_score":12},{"word":"CALESA","scrabble_score":8,"wwf_score":10},{"word":"CAMBIA","scrabble_score":12,"wwf_score":15},{"word":"CAMERA","scrabble_score":10,"wwf_score":12},{"word":"CAMISA","scrabble_score":10,"wwf_score":12},{"word":"CANCHA","scrabble_score":13,"wwf_score":15},{"word":"CANOLA","scrabble_score":8,"wwf_score":11},{"word":"CANULA","scrabble_score":8,"wwf_score":12},{"word":"CAPITA","scrabble_score":10,"wwf_score":12},{"word":"CARDIA","scrabble_score":9,"wwf_score":10},{"word":"CARINA","scrabble_score":8,"wwf_score":10},{"word":"CASABA","scrabble_score":10,"wwf_score":12},{"word":"CASAVA","scrabble_score":11,"wwf_score":13},{"word":"CASITA","scrabble_score":8,"wwf_score":9},{"word":"CASSIA","scrabble_score":8,"wwf_score":9},{"word":"CATENA","scrabble_score":8,"wwf_score":10},{"word":"CEDULA","scrabble_score":9,"wwf_score":12},{"word":"CENTRA","scrabble_score":8,"wwf_score":10},{"word":"CESURA","scrabble_score":8,"wwf_score":10},{"word":"CHACMA","scrabble_score":15,"wwf_score":17},{"word":"CHAETA","scrabble_score":11,"wwf_score":11},{"word":"CHAKRA","scrabble_score":15,"wwf_score":15},{"word":"CHALLA","scrabble_score":11,"wwf_score":13},{"word":"CHARKA","scrabble_score":15,"wwf_score":15},{"word":"CHIMLA","scrabble_score":13,"wwf_score":15},{"word":"CHOANA","scrabble_score":11,"wwf_score":12},{"word":"CHOLLA","scrabble_score":11,"wwf_score":13},{"word":"CHOREA","scrabble_score":11,"wwf_score":11},{"word":"CHROMA","scrabble_score":13,"wwf_score":14},{"word":"CHUKKA","scrabble_score":19,"wwf_score":20},{"word":"CHUPPA","scrabble_score":15,"wwf_score":18},{"word":"CICADA","scrabble_score":11,"wwf_score":13},{"word":"CICALA","scrabble_score":10,"wwf_score":13},{"word":"CINEMA","scrabble_score":10,"wwf_score":13},{"word":"CITOLA","scrabble_score":8,"wwf_score":10},{"word":"CLIVIA","scrabble_score":11,"wwf_score":14},{"word":"CLOACA","scrabble_score":10,"wwf_score":13},{"word":"CODEIA","scrabble_score":9,"wwf_score":10},{"word":"CONCHA","scrabble_score":13,"wwf_score":15},{"word":"CONTRA","scrabble_score":8,"wwf_score":10},{"word":"COPPRA","scrabble_score":12,"wwf_score":15},{"word":"COPULA","scrabble_score":10,"wwf_score":14},{"word":"CORNEA","scrabble_score":8,"wwf_score":10},{"word":"CORNUA","scrabble_score":8,"wwf_score":11},{"word":"CORONA","scrabble_score":8,"wwf_score":10},{"word":"CORYZA","scrabble_score":20,"wwf_score":20},{"word":"COWPEA","scrabble_score":13,"wwf_score":15},{"word":"CRANIA","scrabble_score":8,"wwf_score":10},{"word":"CRISSA","scrabble_score":8,"wwf_score":9},{"word":"CRISTA","scrabble_score":8,"wwf_score":9},{"word":"CUESTA","scrabble_score":8,"wwf_score":10},{"word":"CUMBIA","scrabble_score":12,"wwf_score":16},{"word":"CUPOLA","scrabble_score":10,"wwf_score":14},{"word":"CUPULA","scrabble_score":10,"wwf_score":15},{"word":"CURARA","scrabble_score":8,"wwf_score":10},{"word":"DAGOBA","scrabble_score":10,"wwf_score":12},{"word":"DAHLIA","scrabble_score":10,"wwf_score":10},{"word":"DATCHA","scrabble_score":12,"wwf_score":12},{"word":"DATURA","scrabble_score":7,"wwf_score":8},{"word":"DEFLEA","scrabble_score":10,"wwf_score":11},{"word":"DHARMA","scrabble_score":12,"wwf_score":12},{"word":"DHARNA","scrabble_score":10,"wwf_score":10},{"word":"DHOORA","scrabble_score":10,"wwf_score":9},{"word":"DHURNA","scrabble_score":10,"wwf_score":11},{"word":"DUENNA","scrabble_score":7,"wwf_score":10},{"word":"ECZEMA","scrabble_score":19,"wwf_score":21},{"word":"EGESTA","scrabble_score":7,"wwf_score":8},{"word":"EIDOLA","scrabble_score":7,"wwf_score":8},{"word":"EJECTA","scrabble_score":15,"wwf_score":18},{"word":"ELODEA","scrabble_score":7,"wwf_score":8},{"word":"ELUVIA","scrabble_score":9,"wwf_score":12},{"word":"ELYTRA","scrabble_score":9,"wwf_score":9},{"word":"ENCINA","scrabble_score":8,"wwf_score":11},{"word":"ENIGMA","scrabble_score":9,"wwf_score":12},{"word":"ENTERA","scrabble_score":6,"wwf_score":7},{"word":"EPIZOA","scrabble_score":17,"wwf_score":18},{"word":"ERRATA","scrabble_score":6,"wwf_score":6},{"word":"EUPNEA","scrabble_score":8,"wwf_score":11},{"word":"EUREKA","scrabble_score":10,"wwf_score":11},{"word":"EXACTA","scrabble_score":15,"wwf_score":16},{"word":"EXEDRA","scrabble_score":14,"wwf_score":14},{"word":"EXUVIA","scrabble_score":16,"wwf_score":18},{"word":"FACULA","scrabble_score":11,"wwf_score":14},{"word":"FAJITA","scrabble_score":16,"wwf_score":18},{"word":"FANEGA","scrabble_score":10,"wwf_score":12},{"word":"FARINA","scrabble_score":9,"wwf_score":10},{"word":"FASCIA","scrabble_score":11,"wwf_score":12},{"word":"FAVELA","scrabble_score":12,"wwf_score":14},{"word":"FECULA","scrabble_score":11,"wwf_score":14},{"word":"FEDORA","scrabble_score":10,"wwf_score":10},{"word":"FEIJOA","scrabble_score":16,"wwf_score":18},{"word":"FEMORA","scrabble_score":11,"wwf_score":12},{"word":"FERULA","scrabble_score":9,"wwf_score":11},{"word":"FIBULA","scrabble_score":11,"wwf_score":14},{"word":"FIESTA","scrabble_score":9,"wwf_score":9},{"word":"FLAUTA","scrabble_score":9,"wwf_score":11},{"word":"FRAENA","scrabble_score":9,"wwf_score":10},{"word":"FRUSTA","scrabble_score":9,"wwf_score":10},{"word":"FULCRA","scrabble_score":11,"wwf_score":14},{"word":"FUNKIA","scrabble_score":13,"wwf_score":15},{"word":"FUSUMA","scrabble_score":11,"wwf_score":14},{"word":"GALENA","scrabble_score":7,"wwf_score":10},{"word":"GAMBIA","scrabble_score":11,"wwf_score":14},{"word":"GEISHA","scrabble_score":10,"wwf_score":10},{"word":"GELADA","scrabble_score":8,"wwf_score":10},{"word":"GENERA","scrabble_score":7,"wwf_score":9},{"word":"GENEVA","scrabble_score":10,"wwf_score":13},{"word":"GLIOMA","scrabble_score":9,"wwf_score":12},{"word":"GLORIA","scrabble_score":7,"wwf_score":9},{"word":"GLOSSA","scrabble_score":7,"wwf_score":9},{"word":"GOANNA","scrabble_score":7,"wwf_score":10},{"word":"GOTCHA","scrabble_score":12,"wwf_score":13},{"word":"GRAMMA","scrabble_score":11,"wwf_score":14},{"word":"GRAMPA","scrabble_score":11,"wwf_score":14},{"word":"GRAPPA","scrabble_score":11,"wwf_score":14},{"word":"GUINEA","scrabble_score":7,"wwf_score":10},{"word":"GYTTJA","scrabble_score":17,"wwf_score":19},{"word":"HALALA","scrabble_score":9,"wwf_score":10},{"word":"HALLOA","scrabble_score":9,"wwf_score":10},{"word":"HAMADA","scrabble_score":12,"wwf_score":12},{"word":"HANIWA","scrabble_score":12,"wwf_score":12},{"word":"HAWALA","scrabble_score":12,"wwf_score":12},{"word":"HEGIRA","scrabble_score":10,"wwf_score":10},{"word":"HEJIRA","scrabble_score":16,"wwf_score":17},{"word":"HERNIA","scrabble_score":9,"wwf_score":9},{"word":"HILLOA","scrabble_score":9,"wwf_score":10},{"word":"HOLLOA","scrabble_score":9,"wwf_score":10},{"word":"HOOPLA","scrabble_score":11,"wwf_score":12},{"word":"HRYVNA","scrabble_score":15,"wwf_score":15},{"word":"HULLOA","scrabble_score":9,"wwf_score":11},{"word":"HUTZPA","scrabble_score":20,"wwf_score":21},{"word":"HYAENA","scrabble_score":12,"wwf_score":11},{"word":"HYDRIA","scrabble_score":13,"wwf_score":11},{"word":"IGUANA","scrabble_score":7,"wwf_score":10},{"word":"IMPALA","scrabble_score":10,"wwf_score":13},{"word":"INDABA","scrabble_score":9,"wwf_score":11},{"word":"INTIMA","scrabble_score":8,"wwf_score":10},{"word":"ISCHIA","scrabble_score":11,"wwf_score":11},{"word":"JACANA","scrabble_score":15,"wwf_score":19},{"word":"JARINA","scrabble_score":13,"wwf_score":16},{"word":"JEJUNA","scrabble_score":20,"wwf_score":26},{"word":"JERBOA","scrabble_score":15,"wwf_score":18},{"word":"JICAMA","scrabble_score":17,"wwf_score":21},{"word":"JOJOBA","scrabble_score":22,"wwf_score":27},{"word":"JUDOKA","scrabble_score":18,"wwf_score":21},{"word":"JUGULA","scrabble_score":14,"wwf_score":20},{"word":"KABAKA","scrabble_score":16,"wwf_score":17},{"word":"KABALA","scrabble_score":12,"wwf_score":14},{"word":"KABAYA","scrabble_score":15,"wwf_score":15},{"word":"KAHUNA","scrabble_score":13,"wwf_score":14},{"word":"KALMIA","scrabble_score":12,"wwf_score":14},{"word":"KAMALA","scrabble_score":12,"wwf_score":14},{"word":"KERRIA","scrabble_score":10,"wwf_score":10},{"word":"KINARA","scrabble_score":10,"wwf_score":11},{"word":"KINEMA","scrabble_score":12,"wwf_score":14},{"word":"KISHKA","scrabble_score":17,"wwf_score":16},{"word":"KORUNA","scrabble_score":10,"wwf_score":12},{"word":"KWACHA","scrabble_score":18,"wwf_score":18},{"word":"KWANZA","scrabble_score":22,"wwf_score":23},{"word":"LABARA","scrabble_score":8,"wwf_score":10},{"word":"LACUNA","scrabble_score":8,"wwf_score":12},{"word":"LAGUNA","scrabble_score":7,"wwf_score":11},{"word":"LAMBDA","scrabble_score":11,"wwf_score":14},{"word":"LAMINA","scrabble_score":8,"wwf_score":11},{"word":"LATINA","scrabble_score":6,"wwf_score":8},{"word":"LATRIA","scrabble_score":6,"wwf_score":7},{"word":"LEXICA","scrabble_score":15,"wwf_score":17},{"word":"LIGULA","scrabble_score":7,"wwf_score":11},{"word":"LIKUTA","scrabble_score":10,"wwf_score":12},{"word":"LIMINA","scrabble_score":8,"wwf_score":11},{"word":"LINGUA","scrabble_score":7,"wwf_score":11},{"word":"LIPOMA","scrabble_score":10,"wwf_score":13},{"word":"LITHIA","scrabble_score":9,"wwf_score":9},{"word":"LOCHIA","scrabble_score":11,"wwf_score":12},{"word":"LOGGIA","scrabble_score":8,"wwf_score":11},{"word":"LORICA","scrabble_score":8,"wwf_score":10},{"word":"LUMINA","scrabble_score":8,"wwf_score":12},{"word":"LUNULA","scrabble_score":6,"wwf_score":11},{"word":"LUSTRA","scrabble_score":6,"wwf_score":8},{"word":"MACULA","scrabble_score":10,"wwf_score":14},{"word":"MAFFIA","scrabble_score":14,"wwf_score":15},{"word":"MAKUTA","scrabble_score":12,"wwf_score":14},{"word":"MALTHA","scrabble_score":11,"wwf_score":12},{"word":"MANANA","scrabble_score":8,"wwf_score":11},{"word":"MANILA","scrabble_score":8,"wwf_score":11},{"word":"MANTRA","scrabble_score":8,"wwf_score":10},{"word":"MANTUA","scrabble_score":8,"wwf_score":11},{"word":"MARACA","scrabble_score":10,"wwf_score":12},{"word":"MARINA","scrabble_score":8,"wwf_score":10},{"word":"MARKKA","scrabble_score":16,"wwf_score":17},{"word":"MASALA","scrabble_score":8,"wwf_score":10},{"word":"MAXIMA","scrabble_score":17,"wwf_score":19},{"word":"MAZUMA","scrabble_score":19,"wwf_score":22},{"word":"MEDAKA","scrabble_score":13,"wwf_score":14},{"word":"MEDINA","scrabble_score":9,"wwf_score":11},{"word":"MEDUSA","scrabble_score":9,"wwf_score":11},{"word":"MEGARA","scrabble_score":9,"wwf_score":11},{"word":"MELENA","scrabble_score":8,"wwf_score":11},{"word":"METEPA","scrabble_score":10,"wwf_score":12},{"word":"MEZUZA","scrabble_score":26,"wwf_score":28},{"word":"MIASMA","scrabble_score":10,"wwf_score":12},{"word":"MIMOSA","scrabble_score":10,"wwf_score":12},{"word":"MINIMA","scrabble_score":10,"wwf_score":13},{"word":"MIZUNA","scrabble_score":17,"wwf_score":20},{"word":"MODICA","scrabble_score":11,"wwf_score":13},{"word":"MORULA","scrabble_score":8,"wwf_score":11},{"word":"MUCOSA","scrabble_score":10,"wwf_score":13},{"word":"MULETA","scrabble_score":8,"wwf_score":11},{"word":"MURRHA","scrabble_score":11,"wwf_score":12},{"word":"MYOPIA","scrabble_score":13,"wwf_score":14},{"word":"MYRICA","scrabble_score":13,"wwf_score":14},{"word":"MYXOMA","scrabble_score":20,"wwf_score":21},{"word":"NAGANA","scrabble_score":7,"wwf_score":10},{"word":"NAUSEA","scrabble_score":6,"wwf_score":8},{"word":"NEBULA","scrabble_score":8,"wwf_score":12},{"word":"NEPETA","scrabble_score":8,"wwf_score":10},{"word":"NOMINA","scrabble_score":8,"wwf_score":11},{"word":"NOVENA","scrabble_score":9,"wwf_score":12},{"word":"NUMINA","scrabble_score":8,"wwf_score":12},{"word":"NUTRIA","scrabble_score":6,"wwf_score":8},{"word":"NYMPHA","scrabble_score":16,"wwf_score":17},{"word":"OBELIA","scrabble_score":8,"wwf_score":10},{"word":"OCHREA","scrabble_score":11,"wwf_score":11},{"word":"OEDEMA","scrabble_score":9,"wwf_score":10},{"word":"OMENTA","scrabble_score":8,"wwf_score":10},{"word":"OPTIMA","scrabble_score":10,"wwf_score":12},{"word":"ORGANA","scrabble_score":7,"wwf_score":9},{"word":"ORISHA","scrabble_score":9,"wwf_score":8},{"word":"OSCULA","scrabble_score":8,"wwf_score":11},{"word":"OSETRA","scrabble_score":6,"wwf_score":6},{"word":"OTTAVA","scrabble_score":9,"wwf_score":10},{"word":"PAELLA","scrabble_score":8,"wwf_score":11},{"word":"PAGODA","scrabble_score":10,"wwf_score":12},{"word":"PAJAMA","scrabble_score":17,"wwf_score":21},{"word":"PAKEHA","scrabble_score":15,"wwf_score":15},{"word":"PAKORA","scrabble_score":12,"wwf_score":13},{"word":"PALAPA","scrabble_score":10,"wwf_score":13},{"word":"PALLIA","scrabble_score":8,"wwf_score":11},{"word":"PANADA","scrabble_score":9,"wwf_score":11},{"word":"PANAMA","scrabble_score":10,"wwf_score":13},{"word":"PAPAYA","scrabble_score":13,"wwf_score":14},{"word":"PAPULA","scrabble_score":10,"wwf_score":14},{"word":"PARURA","scrabble_score":8,"wwf_score":10},{"word":"PATACA","scrabble_score":10,"wwf_score":12},{"word":"PATINA","scrabble_score":8,"wwf_score":10},{"word":"PAYOLA","scrabble_score":11,"wwf_score":12},{"word":"PELOTA","scrabble_score":8,"wwf_score":10},{"word":"PENNIA","scrabble_score":8,"wwf_score":11},{"word":"PEREIA","scrabble_score":8,"wwf_score":9},{"word":"PESETA","scrabble_score":8,"wwf_score":9},{"word":"PESEWA","scrabble_score":11,"wwf_score":12},{"word":"PHOBIA","scrabble_score":13,"wwf_score":14},{"word":"PIAZZA","scrabble_score":26,"wwf_score":27},{"word":"PICARA","scrabble_score":10,"wwf_score":12},{"word":"PINATA","scrabble_score":8,"wwf_score":10},{"word":"PINETA","scrabble_score":8,"wwf_score":10},{"word":"PIRANA","scrabble_score":8,"wwf_score":10},{"word":"PIRAYA","scrabble_score":11,"wwf_score":11},{"word":"PITAYA","scrabble_score":11,"wwf_score":11},{"word":"PLASMA","scrabble_score":10,"wwf_score":13},{"word":"PLEURA","scrabble_score":8,"wwf_score":11},{"word":"PNEUMA","scrabble_score":10,"wwf_score":14},{"word":"POISHA","scrabble_score":11,"wwf_score":11},{"word":"POSADA","scrabble_score":9,"wwf_score":10},{"word":"PRAJNA","scrabble_score":15,"wwf_score":19},{"word":"PROTEA","scrabble_score":8,"wwf_score":9},{"word":"PSYLLA","scrabble_score":11,"wwf_score":13},{"word":"PURANA","scrabble_score":8,"wwf_score":11},{"word":"PYEMIA","scrabble_score":13,"wwf_score":14},{"word":"PYJAMA","scrabble_score":20,"wwf_score":23},{"word":"PYROLA","scrabble_score":11,"wwf_score":12},{"word":"PYURIA","scrabble_score":11,"wwf_score":12},{"word":"QABALA","scrabble_score":17,"wwf_score":19},{"word":"QUAGGA","scrabble_score":17,"wwf_score":20},{"word":"QUALIA","scrabble_score":15,"wwf_score":17},{"word":"QUANTA","scrabble_score":15,"wwf_score":17},{"word":"QUELEA","scrabble_score":15,"wwf_score":17},{"word":"QUINOA","scrabble_score":15,"wwf_score":17},{"word":"QUINTA","scrabble_score":15,"wwf_score":17},{"word":"QUOKKA","scrabble_score":23,"wwf_score":24},{"word":"QUOTHA","scrabble_score":18,"wwf_score":18},{"word":"RADULA","scrabble_score":7,"wwf_score":9},{"word":"RAFFIA","scrabble_score":12,"wwf_score":12},{"word":"RAMADA","scrabble_score":9,"wwf_score":10},{"word":"RAMBLA","scrabble_score":10,"wwf_score":13},{"word":"RAMONA","scrabble_score":8,"wwf_score":10},{"word":"RANULA","scrabble_score":6,"wwf_score":9},{"word":"RAPHIA","scrabble_score":11,"wwf_score":11},{"word":"REALIA","scrabble_score":6,"wwf_score":7},{"word":"REDOWA","scrabble_score":10,"wwf_score":10},{"word":"REGINA","scrabble_score":7,"wwf_score":9},{"word":"REMORA","scrabble_score":8,"wwf_score":9},{"word":"REMUDA","scrabble_score":9,"wwf_score":11},{"word":"RESEDA","scrabble_score":7,"wwf_score":7},{"word":"RETINA","scrabble_score":6,"wwf_score":7},{"word":"RHUMBA","scrabble_score":13,"wwf_score":15},{"word":"RISTRA","scrabble_score":6,"wwf_score":6},{"word":"ROSTRA","scrabble_score":6,"wwf_score":6},{"word":"RUGOLA","scrabble_score":7,"wwf_score":10},{"word":"RUGOSA","scrabble_score":7,"wwf_score":9},{"word":"RUMINA","scrabble_score":8,"wwf_score":11},{"word":"SALINA","scrabble_score":6,"wwf_score":8},{"word":"SALIVA","scrabble_score":9,"wwf_score":11},{"word":"SALVIA","scrabble_score":9,"wwf_score":11},{"word":"SAMARA","scrabble_score":8,"wwf_score":9},{"word":"SAMOSA","scrabble_score":8,"wwf_score":9},{"word":"SANCTA","scrabble_score":8,"wwf_score":10},{"word":"SAPOTA","scrabble_score":8,"wwf_score":9},{"word":"SATARA","scrabble_score":6,"wwf_score":6},{"word":"SCHEMA","scrabble_score":13,"wwf_score":14},{"word":"SCILLA","scrabble_score":8,"wwf_score":11},{"word":"SCLERA","scrabble_score":8,"wwf_score":10},{"word":"SCORIA","scrabble_score":8,"wwf_score":9},{"word":"SCOTIA","scrabble_score":8,"wwf_score":9},{"word":"SCROTA","scrabble_score":8,"wwf_score":9},{"word":"SEMINA","scrabble_score":8,"wwf_score":10},{"word":"SENECA","scrabble_score":8,"wwf_score":10},{"word":"SENEGA","scrabble_score":7,"wwf_score":9},{"word":"SENORA","scrabble_score":6,"wwf_score":7},{"word":"SEROSA","scrabble_score":6,"wwf_score":6},{"word":"SHARIA","scrabble_score":9,"wwf_score":8},{"word":"SHEILA","scrabble_score":9,"wwf_score":9},{"word":"SHELTA","scrabble_score":9,"wwf_score":9},{"word":"SHERPA","scrabble_score":11,"wwf_score":11},{"word":"SIENNA","scrabble_score":6,"wwf_score":8},{"word":"SIERRA","scrabble_score":6,"wwf_score":6},{"word":"SIESTA","scrabble_score":6,"wwf_score":6},{"word":"SIFAKA","scrabble_score":13,"wwf_score":13},{"word":"SILICA","scrabble_score":8,"wwf_score":10},{"word":"SISTRA","scrabble_score":6,"wwf_score":6},{"word":"SMEGMA","scrabble_score":11,"wwf_score":14},{"word":"SOMATA","scrabble_score":8,"wwf_score":9},{"word":"SONATA","scrabble_score":6,"wwf_score":7},{"word":"SPIREA","scrabble_score":8,"wwf_score":9},{"word":"SQUAMA","scrabble_score":17,"wwf_score":19},{"word":"SRADHA","scrabble_score":10,"wwf_score":9},{"word":"STADIA","scrabble_score":7,"wwf_score":7},{"word":"STANZA","scrabble_score":15,"wwf_score":16},{"word":"STELLA","scrabble_score":6,"wwf_score":8},{"word":"STEMMA","scrabble_score":10,"wwf_score":12},{"word":"STERNA","scrabble_score":6,"wwf_score":7},{"word":"STIGMA","scrabble_score":9,"wwf_score":11},{"word":"STRATA","scrabble_score":6,"wwf_score":6},{"word":"STROMA","scrabble_score":8,"wwf_score":9},{"word":"STRUMA","scrabble_score":8,"wwf_score":10},{"word":"SUBSEA","scrabble_score":8,"wwf_score":10},{"word":"SULPHA","scrabble_score":11,"wwf_score":13},{"word":"SYNURA","scrabble_score":9,"wwf_score":10},{"word":"TAENIA","scrabble_score":6,"wwf_score":7},{"word":"TAFFIA","scrabble_score":12,"wwf_score":12},{"word":"TALUKA","scrabble_score":10,"wwf_score":12},{"word":"TANTRA","scrabble_score":6,"wwf_score":7},{"word":"TAPETA","scrabble_score":8,"wwf_score":9},{"word":"TARAMA","scrabble_score":8,"wwf_score":9},{"word":"TARSIA","scrabble_score":6,"wwf_score":6},{"word":"TELEGA","scrabble_score":7,"wwf_score":9},{"word":"TEPHRA","scrabble_score":11,"wwf_score":11},{"word":"TERBIA","scrabble_score":8,"wwf_score":9},{"word":"THORIA","scrabble_score":9,"wwf_score":8},{"word":"THULIA","scrabble_score":9,"wwf_score":10},{"word":"TORULA","scrabble_score":6,"wwf_score":8},{"word":"TRAUMA","scrabble_score":8,"wwf_score":10},{"word":"TRIVIA","scrabble_score":9,"wwf_score":10},{"word":"TROIKA","scrabble_score":10,"wwf_score":10},{"word":"TUNDRA","scrabble_score":7,"wwf_score":9},{"word":"TUNICA","scrabble_score":8,"wwf_score":11},{"word":"ULTIMA","scrabble_score":8,"wwf_score":11},{"word":"UNGULA","scrabble_score":7,"wwf_score":12},{"word":"URANIA","scrabble_score":6,"wwf_score":8},{"word":"UREDIA","scrabble_score":7,"wwf_score":8},{"word":"UREMIA","scrabble_score":8,"wwf_score":10},{"word":"UTOPIA","scrabble_score":8,"wwf_score":10},{"word":"VAGINA","scrabble_score":10,"wwf_score":13},{"word":"VALUTA","scrabble_score":9,"wwf_score":12},{"word":"VESICA","scrabble_score":11,"wwf_score":13},{"word":"VICUNA","scrabble_score":11,"wwf_score":15},{"word":"VIMINA","scrabble_score":11,"wwf_score":14},{"word":"VIZSLA","scrabble_score":18,"wwf_score":20},{"word":"VOMICA","scrabble_score":13,"wwf_score":16},{"word":"WOMERA","scrabble_score":11,"wwf_score":12},{"word":"YAKUZA","scrabble_score":22,"wwf_score":22},{"word":"YANTRA","scrabble_score":9,"wwf_score":9},{"word":"YAUTIA","scrabble_score":9,"wwf_score":9},{"word":"YTTRIA","scrabble_score":9,"wwf_score":8},{"word":"ZANANA","scrabble_score":15,"wwf_score":17},{"word":"ZAREBA","scrabble_score":17,"wwf_score":18},{"word":"ZARIBA","scrabble_score":17,"wwf_score":18},{"word":"ZENANA","scrabble_score":15,"wwf_score":17},{"word":"ZEUGMA","scrabble_score":18,"wwf_score":21},{"word":"ZINNIA","scrabble_score":15,"wwf_score":17},{"word":"ZOARIA","scrabble_score":15,"wwf_score":15},{"word":"ZOECIA","scrabble_score":17,"wwf_score":18},{"word":"ZONULA","scrabble_score":15,"wwf_score":18},{"word":"ZOYSIA","scrabble_score":18,"wwf_score":17},{"word":"ZYGOMA","scrabble_score":21,"wwf_score":22}],"7":[{"word":"ABOMASA","scrabble_score":11,"wwf_score":13},{"word":"ABOULIA","scrabble_score":9,"wwf_score":12},{"word":"ABROSIA","scrabble_score":9,"wwf_score":10},{"word":"ACANTHA","scrabble_score":12,"wwf_score":13},{"word":"ACAPNIA","scrabble_score":11,"wwf_score":14},{"word":"ACCIDIA","scrabble_score":12,"wwf_score":14},{"word":"ACEQUIA","scrabble_score":18,"wwf_score":20},{"word":"ACEROLA","scrabble_score":9,"wwf_score":11},{"word":"ACHOLIA","scrabble_score":12,"wwf_score":13},{"word":"ACICULA","scrabble_score":11,"wwf_score":15},{"word":"ACRASIA","scrabble_score":9,"wwf_score":10},{"word":"ACROMIA","scrabble_score":11,"wwf_score":13},{"word":"ACTINIA","scrabble_score":9,"wwf_score":11},{"word":"ADDENDA","scrabble_score":10,"wwf_score":11},{"word":"ADENOMA","scrabble_score":10,"wwf_score":12},{"word":"AECIDIA","scrabble_score":10,"wwf_score":11},{"word":"AEROBIA","scrabble_score":9,"wwf_score":10},{"word":"AGNOSIA","scrabble_score":8,"wwf_score":10},{"word":"AGRAPHA","scrabble_score":13,"wwf_score":14},{"word":"ALAMEDA","scrabble_score":10,"wwf_score":12},{"word":"ALBIZIA","scrabble_score":18,"wwf_score":20},{"word":"ALFALFA","scrabble_score":13,"wwf_score":15},{"word":"ALFORJA","scrabble_score":17,"wwf_score":20},{"word":"ALGEBRA","scrabble_score":10,"wwf_score":13},{"word":"ALLODIA","scrabble_score":8,"wwf_score":10},{"word":"ALLUVIA","scrabble_score":10,"wwf_score":14},{"word":"ALTHAEA","scrabble_score":10,"wwf_score":10},{"word":"ALUMINA","scrabble_score":9,"wwf_score":13},{"word":"AMANITA","scrabble_score":9,"wwf_score":11},{"word":"AMBOINA","scrabble_score":11,"wwf_score":14},{"word":"AMBOYNA","scrabble_score":14,"wwf_score":16},{"word":"AMENTIA","scrabble_score":9,"wwf_score":11},{"word":"AMMONIA","scrabble_score":11,"wwf_score":14},{"word":"AMNESIA","scrabble_score":9,"wwf_score":11},{"word":"AMPHORA","scrabble_score":14,"wwf_score":15},{"word":"AMPULLA","scrabble_score":11,"wwf_score":16},{"word":"AMREETA","scrabble_score":9,"wwf_score":10},{"word":"ANAEMIA","scrabble_score":9,"wwf_score":11},{"word":"ANALGIA","scrabble_score":8,"wwf_score":11},{"word":"ANCHUSA","scrabble_score":12,"wwf_score":14},{"word":"ANCILLA","scrabble_score":9,"wwf_score":13},{"word":"ANERGIA","scrabble_score":8,"wwf_score":10},{"word":"ANGARIA","scrabble_score":8,"wwf_score":10},{"word":"ANGIOMA","scrabble_score":10,"wwf_score":13},{"word":"ANHINGA","scrabble_score":11,"wwf_score":13},{"word":"ANOPSIA","scrabble_score":9,"wwf_score":11},{"word":"ANOSMIA","scrabble_score":9,"wwf_score":11},{"word":"ANTENNA","scrabble_score":7,"wwf_score":10},{"word":"APHAGIA","scrabble_score":13,"wwf_score":14},{"word":"APHASIA","scrabble_score":12,"wwf_score":12},{"word":"APHELIA","scrabble_score":12,"wwf_score":13},{"word":"APHONIA","scrabble_score":12,"wwf_score":13},{"word":"APLASIA","scrabble_score":9,"wwf_score":11},{"word":"APRAXIA","scrabble_score":16,"wwf_score":17},{"word":"APTERIA","scrabble_score":9,"wwf_score":10},{"word":"AQUARIA","scrabble_score":16,"wwf_score":17},{"word":"ARABICA","scrabble_score":11,"wwf_score":13},{"word":"ARAROBA","scrabble_score":9,"wwf_score":10},{"word":"ARCADIA","scrabble_score":10,"wwf_score":11},{"word":"ARCHAEA","scrabble_score":12,"wwf_score":12},{"word":"ARIETTA","scrabble_score":7,"wwf_score":7},{"word":"ARMILLA","scrabble_score":9,"wwf_score":12},{"word":"ARUGOLA","scrabble_score":8,"wwf_score":11},{"word":"ARUGULA","scrabble_score":8,"wwf_score":12},{"word":"ASCIDIA","scrabble_score":10,"wwf_score":11},{"word":"ASTASIA","scrabble_score":7,"wwf_score":7},{"word":"ASTERIA","scrabble_score":7,"wwf_score":7},{"word":"ATALAYA","scrabble_score":10,"wwf_score":10},{"word":"ATEMOYA","scrabble_score":12,"wwf_score":12},{"word":"ATRESIA","scrabble_score":7,"wwf_score":7},{"word":"AUREOLA","scrabble_score":7,"wwf_score":9},{"word":"BABESIA","scrabble_score":11,"wwf_score":13},{"word":"BACCARA","scrabble_score":13,"wwf_score":16},{"word":"BAKLAVA","scrabble_score":16,"wwf_score":19},{"word":"BAKLAWA","scrabble_score":16,"wwf_score":18},{"word":"BANDANA","scrabble_score":10,"wwf_score":13},{"word":"BANDORA","scrabble_score":10,"wwf_score":12},{"word":"BANKSIA","scrabble_score":13,"wwf_score":15},{"word":"BARILLA","scrabble_score":9,"wwf_score":12},{"word":"BARISTA","scrabble_score":9,"wwf_score":10},{"word":"BASIDIA","scrabble_score":10,"wwf_score":11},{"word":"BAZOOKA","scrabble_score":22,"wwf_score":23},{"word":"BEGONIA","scrabble_score":10,"wwf_score":13},{"word":"BEGORRA","scrabble_score":10,"wwf_score":12},{"word":"BERETTA","scrabble_score":9,"wwf_score":10},{"word":"BHANGRA","scrabble_score":13,"wwf_score":15},{"word":"BIDARKA","scrabble_score":14,"wwf_score":15},{"word":"BIENNIA","scrabble_score":9,"wwf_score":12},{"word":"BIRETTA","scrabble_score":9,"wwf_score":10},{"word":"BISNAGA","scrabble_score":10,"wwf_score":13},{"word":"BIZNAGA","scrabble_score":19,"wwf_score":22},{"word":"BOFFOLA","scrabble_score":15,"wwf_score":17},{"word":"BOHEMIA","scrabble_score":14,"wwf_score":15},{"word":"BOLIVIA","scrabble_score":12,"wwf_score":15},{"word":"BOLOGNA","scrabble_score":10,"wwf_score":14},{"word":"BONANZA","scrabble_score":18,"wwf_score":21},{"word":"BOTHRIA","scrabble_score":12,"wwf_score":12},{"word":"BRACHIA","scrabble_score":14,"wwf_score":15},{"word":"BRAVURA","scrabble_score":12,"wwf_score":15},{"word":"BRECCIA","scrabble_score":13,"wwf_score":16},{"word":"BRITSKA","scrabble_score":13,"wwf_score":14},{"word":"BRITZKA","scrabble_score":22,"wwf_score":23},{"word":"BUBINGA","scrabble_score":12,"wwf_score":17},{"word":"BULIMIA","scrabble_score":11,"wwf_score":15},{"word":"BUMELIA","scrabble_score":11,"wwf_score":15},{"word":"BURSERA","scrabble_score":9,"wwf_score":11},{"word":"BUZUKIA","scrabble_score":22,"wwf_score":25},{"word":"CABBALA","scrabble_score":13,"wwf_score":17},{"word":"CABOMBA","scrabble_score":15,"wwf_score":19},{"word":"CADENZA","scrabble_score":19,"wwf_score":21},{"word":"CAESURA","scrabble_score":9,"wwf_score":11},{"word":"CALDERA","scrabble_score":10,"wwf_score":12},{"word":"CAMELIA","scrabble_score":11,"wwf_score":14},{"word":"CAMISIA","scrabble_score":11,"wwf_score":13},{"word":"CAMORRA","scrabble_score":11,"wwf_score":13},{"word":"CANASTA","scrabble_score":9,"wwf_score":11},{"word":"CANDELA","scrabble_score":10,"wwf_score":13},{"word":"CANDIDA","scrabble_score":11,"wwf_score":13},{"word":"CANELLA","scrabble_score":9,"wwf_score":13},{"word":"CANNULA","scrabble_score":9,"wwf_score":14},{"word":"CANTALA","scrabble_score":9,"wwf_score":12},{"word":"CANTATA","scrabble_score":9,"wwf_score":11},{"word":"CANTINA","scrabble_score":9,"wwf_score":12},{"word":"CANZONA","scrabble_score":18,"wwf_score":21},{"word":"CARAMBA","scrabble_score":13,"wwf_score":16},{"word":"CARBORA","scrabble_score":11,"wwf_score":13},{"word":"CARIOCA","scrabble_score":11,"wwf_score":13},{"word":"CASCARA","scrabble_score":11,"wwf_score":13},{"word":"CASSABA","scrabble_score":11,"wwf_score":13},{"word":"CASSATA","scrabble_score":9,"wwf_score":10},{"word":"CASSAVA","scrabble_score":12,"wwf_score":14},{"word":"CASSENA","scrabble_score":9,"wwf_score":11},{"word":"CASSINA","scrabble_score":9,"wwf_score":11},{"word":"CATALPA","scrabble_score":11,"wwf_score":14},{"word":"CATAWBA","scrabble_score":14,"wwf_score":16},{"word":"CAVALLA","scrabble_score":12,"wwf_score":16},{"word":"CEDILLA","scrabble_score":10,"wwf_score":13},{"word":"CELESTA","scrabble_score":9,"wwf_score":11},{"word":"CELOSIA","scrabble_score":9,"wwf_score":11},{"word":"CEMENTA","scrabble_score":11,"wwf_score":14},{"word":"CEREBRA","scrabble_score":11,"wwf_score":13},{"word":"CERVEZA","scrabble_score":21,"wwf_score":23},{"word":"CHACHKA","scrabble_score":21,"wwf_score":21},{"word":"CHALAZA","scrabble_score":21,"wwf_score":22},{"word":"CHALUPA","scrabble_score":14,"wwf_score":17},{"word":"CHAMISA","scrabble_score":14,"wwf_score":15},{"word":"CHARKHA","scrabble_score":19,"wwf_score":18},{"word":"CHIASMA","scrabble_score":14,"wwf_score":15},{"word":"CHIMERA","scrabble_score":14,"wwf_score":15},{"word":"CHOLERA","scrabble_score":12,"wwf_score":13},{"word":"CHRISMA","scrabble_score":14,"wwf_score":15},{"word":"CHUTZPA","scrabble_score":23,"wwf_score":25},{"word":"CIBORIA","scrabble_score":11,"wwf_score":13},{"word":"CINGULA","scrabble_score":10,"wwf_score":15},{"word":"CITHARA","scrabble_score":12,"wwf_score":12},{"word":"CLARKIA","scrabble_score":13,"wwf_score":15},{"word":"COAGULA","scrabble_score":10,"wwf_score":14},{"word":"COCHLEA","scrabble_score":14,"wwf_score":16},{"word":"CODEINA","scrabble_score":10,"wwf_score":12},{"word":"COMITIA","scrabble_score":11,"wwf_score":13},{"word":"COMMATA","scrabble_score":13,"wwf_score":16},{"word":"CONIDIA","scrabble_score":10,"wwf_score":12},{"word":"COPAIBA","scrabble_score":13,"wwf_score":16},{"word":"COQUINA","scrabble_score":18,"wwf_score":21},{"word":"CORBINA","scrabble_score":11,"wwf_score":14},{"word":"CORDOBA","scrabble_score":12,"wwf_score":14},{"word":"COREMIA","scrabble_score":11,"wwf_score":13},{"word":"COROLLA","scrabble_score":9,"wwf_score":12},{"word":"CORPORA","scrabble_score":11,"wwf_score":13},{"word":"CORRIDA","scrabble_score":10,"wwf_score":11},{"word":"CORTINA","scrabble_score":9,"wwf_score":11},{"word":"CORVINA","scrabble_score":12,"wwf_score":15},{"word":"COTINGA","scrabble_score":10,"wwf_score":13},{"word":"CRAPOLA","scrabble_score":11,"wwf_score":14},{"word":"CURACOA","scrabble_score":11,"wwf_score":14},{"word":"CURCUMA","scrabble_score":13,"wwf_score":18},{"word":"CURIOSA","scrabble_score":9,"wwf_score":11},{"word":"CYMATIA","scrabble_score":14,"wwf_score":15},{"word":"CYPSELA","scrabble_score":14,"wwf_score":16},{"word":"CZARINA","scrabble_score":18,"wwf_score":20},{"word":"DAMIANA","scrabble_score":10,"wwf_score":12},{"word":"DAPHNIA","scrabble_score":13,"wwf_score":14},{"word":"DECIDUA","scrabble_score":11,"wwf_score":13},{"word":"DEJECTA","scrabble_score":17,"wwf_score":20},{"word":"DELIRIA","scrabble_score":8,"wwf_score":9},{"word":"DEODARA","scrabble_score":9,"wwf_score":9},{"word":"DEUTZIA","scrabble_score":17,"wwf_score":18},{"word":"DHOURRA","scrabble_score":11,"wwf_score":11},{"word":"DICAMBA","scrabble_score":14,"wwf_score":17},{"word":"DIGAMMA","scrabble_score":13,"wwf_score":16},{"word":"DILEMMA","scrabble_score":12,"wwf_score":15},{"word":"DILUVIA","scrabble_score":11,"wwf_score":14},{"word":"DIORAMA","scrabble_score":10,"wwf_score":11},{"word":"DIPLOMA","scrabble_score":12,"wwf_score":15},{"word":"DIPTERA","scrabble_score":10,"wwf_score":11},{"word":"DIPTYCA","scrabble_score":15,"wwf_score":16},{"word":"DOGMATA","scrabble_score":11,"wwf_score":13},{"word":"DONGOLA","scrabble_score":9,"wwf_score":12},{"word":"DRACENA","scrabble_score":10,"wwf_score":12},{"word":"DRACHMA","scrabble_score":15,"wwf_score":16},{"word":"DROSERA","scrabble_score":8,"wwf_score":8},{"word":"DUODENA","scrabble_score":9,"wwf_score":11},{"word":"DYSPNEA","scrabble_score":13,"wwf_score":14},{"word":"DYSURIA","scrabble_score":11,"wwf_score":11},{"word":"ECHIDNA","scrabble_score":13,"wwf_score":14},{"word":"ECTHYMA","scrabble_score":17,"wwf_score":17},{"word":"ECTOPIA","scrabble_score":11,"wwf_score":13},{"word":"ECTOZOA","scrabble_score":18,"wwf_score":19},{"word":"EDEMATA","scrabble_score":10,"wwf_score":11},{"word":"EMERITA","scrabble_score":9,"wwf_score":10},{"word":"EMPORIA","scrabble_score":11,"wwf_score":13},{"word":"EMPYEMA","scrabble_score":16,"wwf_score":18},{"word":"ENCOMIA","scrabble_score":11,"wwf_score":14},{"word":"ENEMATA","scrabble_score":9,"wwf_score":11},{"word":"ENTASIA","scrabble_score":7,"wwf_score":8},{"word":"ENTOZOA","scrabble_score":16,"wwf_score":17},{"word":"EPHEDRA","scrabble_score":13,"wwf_score":13},{"word":"EPISCIA","scrabble_score":11,"wwf_score":13},{"word":"EROTICA","scrabble_score":9,"wwf_score":10},{"word":"EUGENIA","scrabble_score":8,"wwf_score":11},{"word":"EUGLENA","scrabble_score":8,"wwf_score":12},{"word":"EULOGIA","scrabble_score":8,"wwf_score":11},{"word":"EUPNOEA","scrabble_score":9,"wwf_score":12},{"word":"EXCRETA","scrabble_score":16,"wwf_score":17},{"word":"EXEMPLA","scrabble_score":18,"wwf_score":21},{"word":"EXHEDRA","scrabble_score":18,"wwf_score":17},{"word":"EXORDIA","scrabble_score":15,"wwf_score":15},{"word":"EXOTICA","scrabble_score":16,"wwf_score":17},{"word":"EXTREMA","scrabble_score":16,"wwf_score":17},{"word":"EXURBIA","scrabble_score":16,"wwf_score":18},{"word":"FALBALA","scrabble_score":12,"wwf_score":15},{"word":"FARINHA","scrabble_score":13,"wwf_score":13},{"word":"FAVELLA","scrabble_score":13,"wwf_score":16},{"word":"FAZENDA","scrabble_score":20,"wwf_score":21},{"word":"FELUCCA","scrabble_score":14,"wwf_score":18},{"word":"FERMATA","scrabble_score":12,"wwf_score":13},{"word":"FIBROMA","scrabble_score":14,"wwf_score":16},{"word":"FILARIA","scrabble_score":10,"wwf_score":11},{"word":"FIMBRIA","scrabble_score":14,"wwf_score":16},{"word":"FISTULA","scrabble_score":10,"wwf_score":12},{"word":"FONTINA","scrabble_score":10,"wwf_score":12},{"word":"FORMICA","scrabble_score":14,"wwf_score":16},{"word":"FORMULA","scrabble_score":12,"wwf_score":15},{"word":"FOVEOLA","scrabble_score":13,"wwf_score":15},{"word":"FREESIA","scrabble_score":10,"wwf_score":10},{"word":"FRENULA","scrabble_score":10,"wwf_score":13},{"word":"FUCHSIA","scrabble_score":15,"wwf_score":16},{"word":"FURCULA","scrabble_score":12,"wwf_score":16},{"word":"FUSARIA","scrabble_score":10,"wwf_score":11},{"word":"GALABIA","scrabble_score":10,"wwf_score":13},{"word":"GALANGA","scrabble_score":9,"wwf_score":13},{"word":"GALATEA","scrabble_score":8,"wwf_score":10},{"word":"GALLETA","scrabble_score":8,"wwf_score":11},{"word":"GALLICA","scrabble_score":10,"wwf_score":14},{"word":"GANGLIA","scrabble_score":9,"wwf_score":13},{"word":"GANGSTA","scrabble_score":9,"wwf_score":12},{"word":"GASTREA","scrabble_score":8,"wwf_score":9},{"word":"GAZANIA","scrabble_score":17,"wwf_score":19},{"word":"GERBERA","scrabble_score":10,"wwf_score":12},{"word":"GERMINA","scrabble_score":10,"wwf_score":13},{"word":"GIARDIA","scrabble_score":9,"wwf_score":10},{"word":"GINGIVA","scrabble_score":12,"wwf_score":16},{"word":"GLOMERA","scrabble_score":10,"wwf_score":13},{"word":"GODETIA","scrabble_score":9,"wwf_score":10},{"word":"GONDOLA","scrabble_score":9,"wwf_score":12},{"word":"GONIDIA","scrabble_score":9,"wwf_score":11},{"word":"GORDITA","scrabble_score":9,"wwf_score":10},{"word":"GORILLA","scrabble_score":8,"wwf_score":11},{"word":"GRANDMA","scrabble_score":11,"wwf_score":14},{"word":"GRANDPA","scrabble_score":11,"wwf_score":14},{"word":"GRANITA","scrabble_score":8,"wwf_score":10},{"word":"GRANOLA","scrabble_score":8,"wwf_score":11},{"word":"GRAVIDA","scrabble_score":12,"wwf_score":14},{"word":"GUARANA","scrabble_score":8,"wwf_score":11},{"word":"GUMMATA","scrabble_score":12,"wwf_score":16},{"word":"GYNECIA","scrabble_score":13,"wwf_score":15},{"word":"HAFTARA","scrabble_score":13,"wwf_score":12},{"word":"HAGGADA","scrabble_score":13,"wwf_score":14},{"word":"HALACHA","scrabble_score":15,"wwf_score":15},{"word":"HALAKHA","scrabble_score":17,"wwf_score":16},{"word":"HAMMADA","scrabble_score":15,"wwf_score":16},{"word":"HARIANA","scrabble_score":10,"wwf_score":10},{"word":"HARISSA","scrabble_score":10,"wwf_score":9},{"word":"HELLUVA","scrabble_score":13,"wwf_score":16},{"word":"HEMIOLA","scrabble_score":12,"wwf_score":13},{"word":"HETAERA","scrabble_score":10,"wwf_score":9},{"word":"HETAIRA","scrabble_score":10,"wwf_score":9},{"word":"HEXAPLA","scrabble_score":19,"wwf_score":20},{"word":"HIMATIA","scrabble_score":12,"wwf_score":12},{"word":"HOSANNA","scrabble_score":10,"wwf_score":11},{"word":"HRYVNIA","scrabble_score":16,"wwf_score":16},{"word":"HYMENIA","scrabble_score":15,"wwf_score":15},{"word":"HYPOGEA","scrabble_score":16,"wwf_score":16},{"word":"HYPONEA","scrabble_score":15,"wwf_score":15},{"word":"HYPOXIA","scrabble_score":22,"wwf_score":21},{"word":"IGNATIA","scrabble_score":8,"wwf_score":10},{"word":"IKEBANA","scrabble_score":13,"wwf_score":15},{"word":"ILLUVIA","scrabble_score":10,"wwf_score":14},{"word":"IMPERIA","scrabble_score":11,"wwf_score":13},{"word":"IMPRESA","scrabble_score":11,"wwf_score":13},{"word":"INDICIA","scrabble_score":10,"wwf_score":12},{"word":"INDUSIA","scrabble_score":8,"wwf_score":10},{"word":"INEDITA","scrabble_score":8,"wwf_score":9},{"word":"INERTIA","scrabble_score":7,"wwf_score":8},{"word":"INFANTA","scrabble_score":10,"wwf_score":12},{"word":"INFAUNA","scrabble_score":10,"wwf_score":13},{"word":"INGESTA","scrabble_score":8,"wwf_score":10},{"word":"INOCULA","scrabble_score":9,"wwf_score":13},{"word":"IPOMOEA","scrabble_score":11,"wwf_score":13},{"word":"JELLABA","scrabble_score":16,"wwf_score":21},{"word":"KABBALA","scrabble_score":15,"wwf_score":18},{"word":"KACHINA","scrabble_score":16,"wwf_score":17},{"word":"KALIMBA","scrabble_score":15,"wwf_score":18},{"word":"KATCINA","scrabble_score":13,"wwf_score":15},{"word":"KATSURA","scrabble_score":11,"wwf_score":12},{"word":"KEITLOA","scrabble_score":11,"wwf_score":12},{"word":"KERYGMA","scrabble_score":17,"wwf_score":18},{"word":"KHALIFA","scrabble_score":17,"wwf_score":17},{"word":"KITHARA","scrabble_score":14,"wwf_score":13},{"word":"KOPIYKA","scrabble_score":20,"wwf_score":20},{"word":"LABELLA","scrabble_score":9,"wwf_score":13},{"word":"LAMBADA","scrabble_score":12,"wwf_score":15},{"word":"LAMELLA","scrabble_score":9,"wwf_score":13},{"word":"LANTANA","scrabble_score":7,"wwf_score":10},{"word":"LASAGNA","scrabble_score":8,"wwf_score":11},{"word":"LATAKIA","scrabble_score":11,"wwf_score":12},{"word":"LATILLA","scrabble_score":7,"wwf_score":10},{"word":"LEMMATA","scrabble_score":11,"wwf_score":14},{"word":"LEMPIRA","scrabble_score":11,"wwf_score":14},{"word":"LEUCOMA","scrabble_score":11,"wwf_score":15},{"word":"LEUKOMA","scrabble_score":13,"wwf_score":16},{"word":"LINGULA","scrabble_score":8,"wwf_score":13},{"word":"LIXIVIA","scrabble_score":17,"wwf_score":19},{"word":"LOBELIA","scrabble_score":9,"wwf_score":12},{"word":"LOCUSTA","scrabble_score":9,"wwf_score":12},{"word":"LOGANIA","scrabble_score":8,"wwf_score":11},{"word":"LOMENTA","scrabble_score":9,"wwf_score":12},{"word":"LORDOMA","scrabble_score":10,"wwf_score":12},{"word":"MACCHIA","scrabble_score":16,"wwf_score":18},{"word":"MACUMBA","scrabble_score":15,"wwf_score":20},{"word":"MADEIRA","scrabble_score":10,"wwf_score":11},{"word":"MADONNA","scrabble_score":10,"wwf_score":13},{"word":"MADRASA","scrabble_score":10,"wwf_score":11},{"word":"MADRONA","scrabble_score":10,"wwf_score":12},{"word":"MAGENTA","scrabble_score":10,"wwf_score":13},{"word":"MAGMATA","scrabble_score":12,"wwf_score":15},{"word":"MAHATMA","scrabble_score":14,"wwf_score":15},{"word":"MAHONIA","scrabble_score":12,"wwf_score":13},{"word":"MAJAGUA","scrabble_score":17,"wwf_score":22},{"word":"MALACCA","scrabble_score":13,"wwf_score":17},{"word":"MALANGA","scrabble_score":10,"wwf_score":14},{"word":"MALARIA","scrabble_score":9,"wwf_score":11},{"word":"MANDALA","scrabble_score":10,"wwf_score":13},{"word":"MANDOLA","scrabble_score":10,"wwf_score":13},{"word":"MANILLA","scrabble_score":9,"wwf_score":13},{"word":"MANIOCA","scrabble_score":11,"wwf_score":14},{"word":"MAQUILA","scrabble_score":18,"wwf_score":21},{"word":"MARANTA","scrabble_score":9,"wwf_score":11},{"word":"MARASCA","scrabble_score":11,"wwf_score":13},{"word":"MAREMMA","scrabble_score":13,"wwf_score":16},{"word":"MARIMBA","scrabble_score":13,"wwf_score":16},{"word":"MARKKAA","scrabble_score":17,"wwf_score":18},{"word":"MARSALA","scrabble_score":9,"wwf_score":11},{"word":"MASCARA","scrabble_score":11,"wwf_score":13},{"word":"MASTABA","scrabble_score":11,"wwf_score":13},{"word":"MATILDA","scrabble_score":10,"wwf_score":12},{"word":"MAXILLA","scrabble_score":16,"wwf_score":19},{"word":"MAZURKA","scrabble_score":22,"wwf_score":24},{"word":"MEDULLA","scrabble_score":10,"wwf_score":14},{"word":"MEGILLA","scrabble_score":10,"wwf_score":14},{"word":"MELISMA","scrabble_score":11,"wwf_score":14},{"word":"MELODIA","scrabble_score":10,"wwf_score":12},{"word":"MEROPIA","scrabble_score":11,"wwf_score":13},{"word":"MESHUGA","scrabble_score":13,"wwf_score":15},{"word":"MESTIZA","scrabble_score":18,"wwf_score":19},{"word":"METAZOA","scrabble_score":18,"wwf_score":19},{"word":"MICELLA","scrabble_score":11,"wwf_score":15},{"word":"MILITIA","scrabble_score":9,"wwf_score":11},{"word":"MINORCA","scrabble_score":11,"wwf_score":14},{"word":"MINUTIA","scrabble_score":9,"wwf_score":12},{"word":"MOCHILA","scrabble_score":14,"wwf_score":16},{"word":"MOJARRA","scrabble_score":16,"wwf_score":19},{"word":"MOMENTA","scrabble_score":11,"wwf_score":14},{"word":"MONARDA","scrabble_score":10,"wwf_score":12},{"word":"MORPHIA","scrabble_score":14,"wwf_score":15},{"word":"MOUSAKA","scrabble_score":13,"wwf_score":15},{"word":"MOVIOLA","scrabble_score":12,"wwf_score":15},{"word":"MOZETTA","scrabble_score":18,"wwf_score":19},{"word":"MYALGIA","scrabble_score":13,"wwf_score":15},{"word":"MYCELIA","scrabble_score":14,"wwf_score":16},{"word":"MYELOMA","scrabble_score":14,"wwf_score":16},{"word":"MYOMATA","scrabble_score":14,"wwf_score":15},{"word":"NANDINA","scrabble_score":8,"wwf_score":11},{"word":"NAPHTHA","scrabble_score":15,"wwf_score":15},{"word":"NARCOMA","scrabble_score":11,"wwf_score":14},{"word":"NEUROMA","scrabble_score":9,"wwf_score":12},{"word":"NEURULA","scrabble_score":7,"wwf_score":11},{"word":"NIGELLA","scrabble_score":8,"wwf_score":12},{"word":"NIRVANA","scrabble_score":10,"wwf_score":13},{"word":"NONCOLA","scrabble_score":9,"wwf_score":13},{"word":"NOUMENA","scrabble_score":9,"wwf_score":13},{"word":"NOVELLA","scrabble_score":10,"wwf_score":14},{"word":"OCARINA","scrabble_score":9,"wwf_score":11},{"word":"OLESTRA","scrabble_score":7,"wwf_score":8},{"word":"OOGONIA","scrabble_score":8,"wwf_score":10},{"word":"OOTHECA","scrabble_score":12,"wwf_score":12},{"word":"OPUNTIA","scrabble_score":9,"wwf_score":12},{"word":"OQUASSA","scrabble_score":16,"wwf_score":17},{"word":"ORGANZA","scrabble_score":17,"wwf_score":19},{"word":"OSMUNDA","scrabble_score":10,"wwf_score":13},{"word":"OSSETRA","scrabble_score":7,"wwf_score":7},{"word":"OSTEOMA","scrabble_score":9,"wwf_score":10},{"word":"OSTRACA","scrabble_score":9,"wwf_score":10},{"word":"OSTRAKA","scrabble_score":11,"wwf_score":11},{"word":"OTALGIA","scrabble_score":8,"wwf_score":10},{"word":"OUGUIYA","scrabble_score":11,"wwf_score":13},{"word":"OVERSEA","scrabble_score":10,"wwf_score":11},{"word":"OVIPARA","scrabble_score":12,"wwf_score":14},{"word":"OXYMORA","scrabble_score":19,"wwf_score":19},{"word":"PAISANA","scrabble_score":9,"wwf_score":11},{"word":"PALABRA","scrabble_score":11,"wwf_score":14},{"word":"PALMYRA","scrabble_score":14,"wwf_score":16},{"word":"PALOOKA","scrabble_score":13,"wwf_score":15},{"word":"PANACEA","scrabble_score":11,"wwf_score":14},{"word":"PANDORA","scrabble_score":10,"wwf_score":12},{"word":"PANDURA","scrabble_score":10,"wwf_score":13},{"word":"PANOCHA","scrabble_score":14,"wwf_score":16},{"word":"PAPILLA","scrabble_score":11,"wwf_score":15},{"word":"PAPRICA","scrabble_score":13,"wwf_score":16},{"word":"PAPRIKA","scrabble_score":15,"wwf_score":17},{"word":"PAREIRA","scrabble_score":9,"wwf_score":10},{"word":"PARERGA","scrabble_score":10,"wwf_score":12},{"word":"PARTITA","scrabble_score":9,"wwf_score":10},{"word":"PASTINA","scrabble_score":9,"wwf_score":11},{"word":"PATAGIA","scrabble_score":10,"wwf_score":12},{"word":"PATELLA","scrabble_score":9,"wwf_score":12},{"word":"PAVLOVA","scrabble_score":15,"wwf_score":19},{"word":"PECULIA","scrabble_score":11,"wwf_score":15},{"word":"PELORIA","scrabble_score":9,"wwf_score":11},{"word":"PEMBINA","scrabble_score":13,"wwf_score":17},{"word":"PERGOLA","scrabble_score":10,"wwf_score":13},{"word":"PERIDIA","scrabble_score":10,"wwf_score":11},{"word":"PERILLA","scrabble_score":9,"wwf_score":12},{"word":"PERINEA","scrabble_score":9,"wwf_score":11},{"word":"PERSONA","scrabble_score":9,"wwf_score":11},{"word":"PETUNIA","scrabble_score":9,"wwf_score":12},{"word":"PHILTRA","scrabble_score":12,"wwf_score":13},{"word":"PIASABA","scrabble_score":11,"wwf_score":13},{"word":"PIASAVA","scrabble_score":12,"wwf_score":14},{"word":"PICCATA","scrabble_score":13,"wwf_score":16},{"word":"PIGNORA","scrabble_score":10,"wwf_score":13},{"word":"PINNULA","scrabble_score":9,"wwf_score":14},{"word":"PINTADA","scrabble_score":10,"wwf_score":12},{"word":"PIRAGUA","scrabble_score":10,"wwf_score":13},{"word":"PIRANHA","scrabble_score":12,"wwf_score":13},{"word":"PISCINA","scrabble_score":11,"wwf_score":14},{"word":"PLANULA","scrabble_score":9,"wwf_score":14},{"word":"PLATINA","scrabble_score":9,"wwf_score":12},{"word":"PLECTRA","scrabble_score":11,"wwf_score":14},{"word":"PLUGOLA","scrabble_score":10,"wwf_score":15},{"word":"PODAGRA","scrabble_score":11,"wwf_score":13},{"word":"PODESTA","scrabble_score":10,"wwf_score":11},{"word":"POGONIA","scrabble_score":10,"wwf_score":13},{"word":"POLENTA","scrabble_score":9,"wwf_score":12},{"word":"POLYNYA","scrabble_score":15,"wwf_score":16},{"word":"POLYOMA","scrabble_score":14,"wwf_score":16},{"word":"PRECAVA","scrabble_score":14,"wwf_score":17},{"word":"PREPUPA","scrabble_score":13,"wwf_score":17},{"word":"PRIMULA","scrabble_score":11,"wwf_score":15},{"word":"PRONOTA","scrabble_score":9,"wwf_score":11},{"word":"PROPRIA","scrabble_score":11,"wwf_score":13},{"word":"PROPYLA","scrabble_score":14,"wwf_score":16},{"word":"PROSOMA","scrabble_score":11,"wwf_score":13},{"word":"PTERYLA","scrabble_score":12,"wwf_score":13},{"word":"PUDENDA","scrabble_score":11,"wwf_score":14},{"word":"PUPARIA","scrabble_score":11,"wwf_score":14},{"word":"PURPURA","scrabble_score":11,"wwf_score":15},{"word":"PYAEMIA","scrabble_score":14,"wwf_score":15},{"word":"PYGIDIA","scrabble_score":14,"wwf_score":15},{"word":"PYREXIA","scrabble_score":19,"wwf_score":19},{"word":"PYXIDIA","scrabble_score":20,"wwf_score":20},{"word":"QUASSIA","scrabble_score":16,"wwf_score":17},{"word":"QUERIDA","scrabble_score":17,"wwf_score":18},{"word":"QUINELA","scrabble_score":16,"wwf_score":19},{"word":"QUININA","scrabble_score":16,"wwf_score":19},{"word":"RAMENTA","scrabble_score":9,"wwf_score":11},{"word":"RASBORA","scrabble_score":9,"wwf_score":10},{"word":"RATAFIA","scrabble_score":10,"wwf_score":10},{"word":"REFUGIA","scrabble_score":11,"wwf_score":13},{"word":"REGALIA","scrabble_score":8,"wwf_score":10},{"word":"REGATTA","scrabble_score":8,"wwf_score":9},{"word":"REGMATA","scrabble_score":10,"wwf_score":12},{"word":"REPLICA","scrabble_score":11,"wwf_score":14},{"word":"RESIDUA","scrabble_score":8,"wwf_score":9},{"word":"RETSINA","scrabble_score":7,"wwf_score":8},{"word":"RHIZOMA","scrabble_score":21,"wwf_score":21},{"word":"RHODORA","scrabble_score":11,"wwf_score":10},{"word":"RICKSHA","scrabble_score":16,"wwf_score":16},{"word":"RICOTTA","scrabble_score":9,"wwf_score":10},{"word":"RIKISHA","scrabble_score":14,"wwf_score":13},{"word":"RIVIERA","scrabble_score":10,"wwf_score":11},{"word":"ROBUSTA","scrabble_score":9,"wwf_score":11},{"word":"ROSACEA","scrabble_score":9,"wwf_score":10},{"word":"ROSARIA","scrabble_score":7,"wwf_score":7},{"word":"ROSEOLA","scrabble_score":7,"wwf_score":8},{"word":"ROTUNDA","scrabble_score":8,"wwf_score":10},{"word":"RUBELLA","scrabble_score":9,"wwf_score":13},{"word":"RUBEOLA","scrabble_score":9,"wwf_score":12},{"word":"RUFIYAA","scrabble_score":13,"wwf_score":13},{"word":"SAMBUCA","scrabble_score":13,"wwf_score":17},{"word":"SAMSARA","scrabble_score":9,"wwf_score":10},{"word":"SANGRIA","scrabble_score":8,"wwf_score":10},{"word":"SANTERA","scrabble_score":7,"wwf_score":8},{"word":"SAPHENA","scrabble_score":12,"wwf_score":13},{"word":"SARCINA","scrabble_score":9,"wwf_score":11},{"word":"SARCOMA","scrabble_score":11,"wwf_score":13},{"word":"SARDANA","scrabble_score":8,"wwf_score":9},{"word":"SATSUMA","scrabble_score":9,"wwf_score":11},{"word":"SAVANNA","scrabble_score":10,"wwf_score":13},{"word":"SAXTUBA","scrabble_score":16,"wwf_score":18},{"word":"SCANDIA","scrabble_score":10,"wwf_score":12},{"word":"SCAPULA","scrabble_score":11,"wwf_score":15},{"word":"SCHOLIA","scrabble_score":12,"wwf_score":13},{"word":"SCOPULA","scrabble_score":11,"wwf_score":15},{"word":"SCOTOMA","scrabble_score":11,"wwf_score":13},{"word":"SEDILIA","scrabble_score":8,"wwf_score":9},{"word":"SENHORA","scrabble_score":10,"wwf_score":10},{"word":"SENOPIA","scrabble_score":9,"wwf_score":11},{"word":"SEQUELA","scrabble_score":16,"wwf_score":18},{"word":"SEQUOIA","scrabble_score":16,"wwf_score":17},{"word":"SERIEMA","scrabble_score":9,"wwf_score":10},{"word":"SERINGA","scrabble_score":8,"wwf_score":10},{"word":"SESTINA","scrabble_score":7,"wwf_score":8},{"word":"SEVRUGA","scrabble_score":11,"wwf_score":14},{"word":"SHORTIA","scrabble_score":10,"wwf_score":9},{"word":"SIGNORA","scrabble_score":8,"wwf_score":10},{"word":"SILESIA","scrabble_score":7,"wwf_score":8},{"word":"SILIQUA","scrabble_score":16,"wwf_score":18},{"word":"SINOPIA","scrabble_score":9,"wwf_score":11},{"word":"SOLARIA","scrabble_score":7,"wwf_score":8},{"word":"SOLATIA","scrabble_score":7,"wwf_score":8},{"word":"SPATULA","scrabble_score":9,"wwf_score":12},{"word":"SPECTRA","scrabble_score":11,"wwf_score":13},{"word":"SPECULA","scrabble_score":11,"wwf_score":15},{"word":"SPICULA","scrabble_score":11,"wwf_score":15},{"word":"SPINULA","scrabble_score":9,"wwf_score":13},{"word":"SPIRAEA","scrabble_score":9,"wwf_score":10},{"word":"SPIRULA","scrabble_score":9,"wwf_score":12},{"word":"SPLENIA","scrabble_score":9,"wwf_score":12},{"word":"SQUILLA","scrabble_score":16,"wwf_score":19},{"word":"SRADDHA","scrabble_score":12,"wwf_score":11},{"word":"STAMINA","scrabble_score":9,"wwf_score":11},{"word":"STASIMA","scrabble_score":9,"wwf_score":10},{"word":"STHENIA","scrabble_score":10,"wwf_score":10},{"word":"STOMATA","scrabble_score":9,"wwf_score":10},{"word":"STRETTA","scrabble_score":7,"wwf_score":7},{"word":"STRIATA","scrabble_score":7,"wwf_score":7},{"word":"SUBAREA","scrabble_score":9,"wwf_score":11},{"word":"SUBIDEA","scrabble_score":10,"wwf_score":12},{"word":"SUBPENA","scrabble_score":11,"wwf_score":15},{"word":"SUBTAXA","scrabble_score":16,"wwf_score":18},{"word":"SUCCUBA","scrabble_score":13,"wwf_score":18},{"word":"SUDARIA","scrabble_score":8,"wwf_score":9},{"word":"SULTANA","scrabble_score":7,"wwf_score":10},{"word":"SYCONIA","scrabble_score":12,"wwf_score":13},{"word":"SYNOVIA","scrabble_score":13,"wwf_score":14},{"word":"SYRINGA","scrabble_score":11,"wwf_score":12},{"word":"TAFFETA","scrabble_score":13,"wwf_score":13},{"word":"TALARIA","scrabble_score":7,"wwf_score":8},{"word":"TALOOKA","scrabble_score":11,"wwf_score":12},{"word":"TAMASHA","scrabble_score":12,"wwf_score":12},{"word":"TAMBALA","scrabble_score":11,"wwf_score":14},{"word":"TAMBURA","scrabble_score":11,"wwf_score":14},{"word":"TAMPALA","scrabble_score":11,"wwf_score":14},{"word":"TANTARA","scrabble_score":7,"wwf_score":8},{"word":"TAPIOCA","scrabble_score":11,"wwf_score":13},{"word":"TARTANA","scrabble_score":7,"wwf_score":8},{"word":"TAVERNA","scrabble_score":10,"wwf_score":12},{"word":"TEGMINA","scrabble_score":10,"wwf_score":13},{"word":"TEMPERA","scrabble_score":11,"wwf_score":13},{"word":"TEMPURA","scrabble_score":11,"wwf_score":14},{"word":"TEQUILA","scrabble_score":16,"wwf_score":18},{"word":"TESSERA","scrabble_score":7,"wwf_score":7},{"word":"TILAPIA","scrabble_score":9,"wwf_score":11},{"word":"TIMPANA","scrabble_score":11,"wwf_score":14},{"word":"TITANIA","scrabble_score":7,"wwf_score":8},{"word":"TOCCATA","scrabble_score":11,"wwf_score":13},{"word":"TOMBOLA","scrabble_score":11,"wwf_score":14},{"word":"TOMENTA","scrabble_score":9,"wwf_score":11},{"word":"TOSTADA","scrabble_score":8,"wwf_score":8},{"word":"TOXEMIA","scrabble_score":16,"wwf_score":17},{"word":"TRACHEA","scrabble_score":12,"wwf_score":12},{"word":"TREHALA","scrabble_score":10,"wwf_score":10},{"word":"TRITOMA","scrabble_score":9,"wwf_score":10},{"word":"TRYMATA","scrabble_score":12,"wwf_score":12},{"word":"TSARINA","scrabble_score":7,"wwf_score":8},{"word":"TUATARA","scrabble_score":7,"wwf_score":8},{"word":"TUATERA","scrabble_score":7,"wwf_score":8},{"word":"TURISTA","scrabble_score":7,"wwf_score":8},{"word":"TYMPANA","scrabble_score":14,"wwf_score":16},{"word":"TZARINA","scrabble_score":16,"wwf_score":17},{"word":"URAEMIA","scrabble_score":9,"wwf_score":11},{"word":"URETHRA","scrabble_score":10,"wwf_score":10},{"word":"VACCINA","scrabble_score":14,"wwf_score":18},{"word":"VALONIA","scrabble_score":10,"wwf_score":13},{"word":"VALVULA","scrabble_score":13,"wwf_score":18},{"word":"VANILLA","scrabble_score":10,"wwf_score":14},{"word":"VARIOLA","scrabble_score":10,"wwf_score":12},{"word":"VASCULA","scrabble_score":12,"wwf_score":16},{"word":"VEDALIA","scrabble_score":11,"wwf_score":13},{"word":"VELARIA","scrabble_score":10,"wwf_score":12},{"word":"VERANDA","scrabble_score":11,"wwf_score":13},{"word":"VERBENA","scrabble_score":12,"wwf_score":15},{"word":"VERRUCA","scrabble_score":12,"wwf_score":15},{"word":"VEXILLA","scrabble_score":17,"wwf_score":20},{"word":"VIATICA","scrabble_score":12,"wwf_score":14},{"word":"VICUGNA","scrabble_score":13,"wwf_score":18},{"word":"VINCULA","scrabble_score":12,"wwf_score":17},{"word":"VIREMIA","scrabble_score":12,"wwf_score":14},{"word":"VISCERA","scrabble_score":12,"wwf_score":14},{"word":"VIVARIA","scrabble_score":13,"wwf_score":15},{"word":"WAKANDA","scrabble_score":15,"wwf_score":16},{"word":"WEIGELA","scrabble_score":11,"wwf_score":13},{"word":"WHOOPLA","scrabble_score":15,"wwf_score":16},{"word":"WOMMERA","scrabble_score":14,"wwf_score":16},{"word":"WOODSIA","scrabble_score":11,"wwf_score":11},{"word":"WOOMERA","scrabble_score":12,"wwf_score":13},{"word":"YAMALKA","scrabble_score":16,"wwf_score":17},{"word":"YAMULKA","scrabble_score":16,"wwf_score":18},{"word":"YESHIVA","scrabble_score":16,"wwf_score":15},{"word":"ZAMARRA","scrabble_score":18,"wwf_score":19},{"word":"ZAREEBA","scrabble_score":18,"wwf_score":19},{"word":"ZELKOVA","scrabble_score":23,"wwf_score":25},{"word":"ZEMSTVA","scrabble_score":21,"wwf_score":23},{"word":"ZENAIDA","scrabble_score":17,"wwf_score":18},{"word":"ZINGARA","scrabble_score":17,"wwf_score":19},{"word":"ZOOECIA","scrabble_score":18,"wwf_score":19},{"word":"ZOOGLEA","scrabble_score":17,"wwf_score":19},{"word":"ZORILLA","scrabble_score":16,"wwf_score":18},{"word":"ZYZZYVA","scrabble_score":43,"wwf_score":42}]}