{"3":[{"word":"ADZ","scrabble_score":13,"wwf_score":13},{"word":"BIZ","scrabble_score":14,"wwf_score":15},{"word":"COZ","scrabble_score":14,"wwf_score":15},{"word":"FEZ","scrabble_score":15,"wwf_score":15},{"word":"FIZ","scrabble_score":15,"wwf_score":15},{"word":"WIZ","scrabble_score":15,"wwf_score":15},{"word":"ZUZ","scrabble_score":21,"wwf_score":22},{"word":"ZZZ","scrabble_score":30,"wwf_score":30}],"4":[{"word":"BUZZ","scrabble_score":24,"wwf_score":26},{"word":"CHEZ","scrabble_score":18,"wwf_score":18},{"word":"DITZ","scrabble_score":14,"wwf_score":14},{"word":"FIZZ","scrabble_score":25,"wwf_score":25},{"word":"FRIZ","scrabble_score":16,"wwf_score":16},{"word":"FUTZ","scrabble_score":16,"wwf_score":17},{"word":"FUZZ","scrabble_score":25,"wwf_score":26},{"word":"GEEZ","scrabble_score":14,"wwf_score":15},{"word":"JAZZ","scrabble_score":29,"wwf_score":31},{"word":"JEEZ","scrabble_score":20,"wwf_score":22},{"word":"LUTZ","scrabble_score":13,"wwf_score":15},{"word":"OYEZ","scrabble_score":16,"wwf_score":15},{"word":"PHIZ","scrabble_score":18,"wwf_score":18},{"word":"PREZ","scrabble_score":15,"wwf_score":16},{"word":"PUTZ","scrabble_score":15,"wwf_score":17},{"word":"QUIZ","scrabble_score":22,"wwf_score":23},{"word":"RAZZ","scrabble_score":22,"wwf_score":22},{"word":"RITZ","scrabble_score":13,"wwf_score":13},{"word":"WHIZ","scrabble_score":19,"wwf_score":18},{"word":"YUTZ","scrabble_score":16,"wwf_score":16}],"5":[{"word":"ABUZZ","scrabble_score":25,"wwf_score":27},{"word":"BLITZ","scrabble_score":16,"wwf_score":18},{"word":"BORTZ","scrabble_score":16,"wwf_score":17},{"word":"CAPIZ","scrabble_score":18,"wwf_score":20},{"word":"FRITZ","scrabble_score":17,"wwf_score":17},{"word":"FRIZZ","scrabble_score":26,"wwf_score":26},{"word":"GLITZ","scrabble_score":15,"wwf_score":17},{"word":"GROSZ","scrabble_score":15,"wwf_score":16},{"word":"HAFIZ","scrabble_score":20,"wwf_score":19},{"word":"HERTZ","scrabble_score":17,"wwf_score":16},{"word":"KLUTZ","scrabble_score":18,"wwf_score":20},{"word":"NERTZ","scrabble_score":14,"wwf_score":15},{"word":"PLOTZ","scrabble_score":16,"wwf_score":18},{"word":"SCUZZ","scrabble_score":25,"wwf_score":27},{"word":"SOYUZ","scrabble_score":17,"wwf_score":17},{"word":"SPITZ","scrabble_score":16,"wwf_score":17},{"word":"TOPAZ","scrabble_score":16,"wwf_score":17},{"word":"TROOZ","scrabble_score":14,"wwf_score":14},{"word":"WALTZ","scrabble_score":17,"wwf_score":18},{"word":"WHIZZ","scrabble_score":29,"wwf_score":28}],"6":[{"word":"BEZAZZ","scrabble_score":35,"wwf_score":36},{"word":"BLINTZ","scrabble_score":17,"wwf_score":20},{"word":"CHINTZ","scrabble_score":20,"wwf_score":21},{"word":"ERSATZ","scrabble_score":15,"wwf_score":15},{"word":"HALUTZ","scrabble_score":18,"wwf_score":19},{"word":"KIBITZ","scrabble_score":21,"wwf_score":22},{"word":"KOLHOZ","scrabble_score":22,"wwf_score":22},{"word":"KOLKOZ","scrabble_score":23,"wwf_score":24},{"word":"KUVASZ","scrabble_score":22,"wwf_score":24},{"word":"PAZAZZ","scrabble_score":35,"wwf_score":36},{"word":"PIZAZZ","scrabble_score":35,"wwf_score":36},{"word":"PIZZAZ","scrabble_score":35,"wwf_score":36},{"word":"QUARTZ","scrabble_score":24,"wwf_score":25},{"word":"SCHNOZ","scrabble_score":20,"wwf_score":21},{"word":"SPELTZ","scrabble_score":17,"wwf_score":19},{"word":"SPRITZ","scrabble_score":17,"wwf_score":18}],"7":[{"word":"CHALUTZ","scrabble_score":21,"wwf_score":23},{"word":"KIBBITZ","scrabble_score":24,"wwf_score":26},{"word":"KIBBUTZ","scrabble_score":24,"wwf_score":27},{"word":"KOLKHOZ","scrabble_score":27,"wwf_score":27},{"word":"PIZZAZZ","scrabble_score":45,"wwf_score":46},{"word":"SCHMALZ","scrabble_score":23,"wwf_score":25},{"word":"SCHNOZZ","scrabble_score":30,"wwf_score":31},{"word":"SHMALTZ","scrabble_score":21,"wwf_score":22},{"word":"SHOWBIZ","scrabble_score":24,"wwf_score":24},{"word":"SOVKHOZ","scrabble_score":26,"wwf_score":26}],"8":[{"word":"EXAHERTZ","scrabble_score":27,"wwf_score":26},{"word":"SCHMALTZ","scrabble_score":24,"wwf_score":26},{"word":"SOLONETZ","scrabble_score":17,"wwf_score":19}],"9":[{"word":"GIGAHERTZ","scrabble_score":23,"wwf_score":24},{"word":"KILOHERTZ","scrabble_score":25,"wwf_score":25},{"word":"KRUMMHOLZ","scrabble_score":29,"wwf_score":32},{"word":"MEGAHERTZ","scrabble_score":24,"wwf_score":25},{"word":"PETAHERTZ","scrabble_score":23,"wwf_score":23},{"word":"RHEUMATIZ","scrabble_score":23,"wwf_score":24},{"word":"SLIVOVITZ","scrabble_score":24,"wwf_score":27},{"word":"TERAHERTZ","scrabble_score":21,"wwf_score":20}],"10":[{"word":"RAZZMATAZZ","scrabble_score":48,"wwf_score":49}],"11":[{"word":"RAZZAMATAZZ","scrabble_score":49,"wwf_score":50},{"word":"WELTSCHMERZ","scrabble_score":30,"wwf_score":32}]}